CLA_16/CLA_16.srcs/sources_1/new/cla_adder_16.v
// 4-bit Carry Look-Ahead Adder
module cla4 (
    input  [3:0] A,
    input  [3:0] B,
    input        Cin,
    output [3:0] Sum,
    output       Cout,
    output       P,
    output       G
);

    wire [3:0] p, g;
    wire [4:0] c;

    assign p = A ^ B;
    assign g = A & B;

    assign c[0] = Cin;

    // Internal carry look-ahead equations
    assign c[1] = g[0] | (p[0] & c[0]);

    assign c[2] = g[1] |
                  (p[1] & g[0]) |
                  (p[1] & p[0] & c[0]);

    assign c[3] = g[2] |
                  (p[2] & g[1]) |
                  (p[2] & p[1] & g[0]) |
                  (p[2] & p[1] & p[0] & c[0]);

    assign c[4] = g[3] |
                  (p[3] & g[2]) |
                  (p[3] & p[2] & g[1]) |
                  (p[3] & p[2] & p[1] & g[0]) |
                  (p[3] & p[2] & p[1] & p[0] & c[0]);

    assign Sum = p ^ c[3:0];
    assign Cout = c[4];

    // Group propagate and generate
    assign P = &p;

    assign G = g[3] |
               (p[3] & g[2]) |
               (p[3] & p[2] & g[1]) |
               (p[3] & p[2] & p[1] & g[0]);

endmodule


// 16-bit Carry Look-Ahead Adder
module cla16 (
    input  [15:0] A,
    input  [15:0] B,
    input         Cin,
    output [15:0] Sum,
    output        Cout
);

    wire [3:0] block_P;
    wire [3:0] block_G;
    wire [4:0] C;

    assign C[0] = Cin;

    // Look-ahead carry equations between 4-bit blocks
    assign C[1] = block_G[0] |
                  (block_P[0] & C[0]);

    assign C[2] = block_G[1] |
                  (block_P[1] & block_G[0]) |
                  (block_P[1] & block_P[0] & C[0]);

    assign C[3] = block_G[2] |
                  (block_P[2] & block_G[1]) |
                  (block_P[2] & block_P[1] & block_G[0]) |
                  (block_P[2] & block_P[1] & block_P[0] & C[0]);

    assign C[4] = block_G[3] |
                  (block_P[3] & block_G[2]) |
                  (block_P[3] & block_P[2] & block_G[1]) |
                  (block_P[3] & block_P[2] & block_P[1] & block_G[0]) |
                  (block_P[3] & block_P[2] & block_P[1] & block_P[0] & C[0]);

    // Four 4-bit CLA blocks
    cla4 CLA0 (
        .A(A[3:0]),
        .B(B[3:0]),
        .Cin(C[0]),
        .Sum(Sum[3:0]),
        .Cout(),
        .P(block_P[0]),
        .G(block_G[0])
    );

    cla4 CLA1 (
        .A(A[7:4]),
        .B(B[7:4]),
        .Cin(C[1]),
        .Sum(Sum[7:4]),
        .Cout(),
        .P(block_P[1]),
        .G(block_G[1])
    );

    cla4 CLA2 (
        .A(A[11:8]),
        .B(B[11:8]),
        .Cin(C[2]),
        .Sum(Sum[11:8]),
        .Cout(),
        .P(block_P[2]),
        .G(block_G[2])
    );

    cla4 CLA3 (
        .A(A[15:12]),
        .B(B[15:12]),
        .Cin(C[3]),
        .Sum(Sum[15:12]),
        .Cout(),
        .P(block_P[3]),
        .G(block_G[3])
    );

    assign Cout = C[4];

endmodule

CLA_16/CLA_16.srcs/sim_1/new/tb_cla_adder_16.v
`timescale 1ns / 1ps

module cla16_tb;

    reg  [15:0] A, B;
    reg         Cin;

    wire [15:0] Sum;
    wire        Cout;

    reg  [16:0] Expected;
    integer i;
    integer pass_count;
    integer fail_count;

    // DUT instantiation
    cla16 DUT (
        .A(A),
        .B(B),
        .Cin(Cin),
        .Sum(Sum),
        .Cout(Cout)
    );

    // Task to apply inputs and verify outputs
    task check_result;
        input [15:0] test_A;
        input [15:0] test_B;
        input        test_Cin;
        begin
            A = test_A;
            B = test_B;
            Cin = test_Cin;

            // Allow combinational logic to settle
            #10;

            // Independent reference calculation
            Expected = {1'b0, A} + {1'b0, B} + Cin;

            if ({Cout, Sum} === Expected) begin
                pass_count = pass_count + 1;
            end
            else begin
                fail_count = fail_count + 1;
                $display("FAIL: A=%h B=%h Cin=%b", A, B, Cin);
                $display("Expected=%h, Actual=%h",
                         Expected, {Cout, Sum});
            end
        end
    endtask

    initial begin
        $dumpfile("cla16.vcd");
        $dumpvars(0, cla16_tb);

        pass_count = 0;
        fail_count = 0;

        // Directed test cases
        check_result(16'h0000, 16'h0000, 1'b0);
        check_result(16'h0000, 16'h0000, 1'b1);
        check_result(16'h0001, 16'h0001, 1'b0);
        check_result(16'hFFFF, 16'h0001, 1'b0);
        check_result(16'hFFFF, 16'hFFFF, 1'b0);
        check_result(16'hFFFF, 16'hFFFF, 1'b1);
        check_result(16'h7FFF, 16'h0001, 1'b0);
        check_result(16'h8000, 16'h8000, 1'b0);
        check_result(16'h0FFF, 16'h0001, 1'b0);
        check_result(16'h00FF, 16'h0001, 1'b0);
        check_result(16'h5555, 16'hAAAA, 1'b0);
        check_result(16'hAAAA, 16'h5555, 1'b1);
        check_result(16'h1111, 16'hEEEE, 1'b0);
        check_result(16'hFFFF, 16'h0000, 1'b1);

        // Randomized test cases
        for (i = 0; i < 1000; i = i + 1) begin
            check_result($random, $random, $random);
        end

        // Final test summary
        $display("--------------------------------");
        $display("16-bit CLA Test Summary");
        $display("Passed: %0d", pass_count);
        $display("Failed: %0d", fail_count);
        $display("--------------------------------");

        if (fail_count == 0)
            $display("TEST RESULT: PASS");
        else
            $display("TEST RESULT: FAIL");

        $finish;
    end

endmodule

CLA_16/CLA_16.sim/sim_1/behav/xsim/cla16.vcd
$date
   Tue Sep 29 15:13:41 2026
$end

$version
  2026.1
  $dumpfile ("cla16.vcd") 
$end

$timescale
  1ps
$end

$scope module cla16_tb $end
$var reg 16 ! A [15:0] $end
$var reg 16 " B [15:0] $end
$var reg 1 # Cin $end
$var wire 16 $ Sum [15:0] $end
$var wire 1 % Cout $end
$var reg 17 & Expected [16:0] $end
$var integer 32 ' i [31:0] $end
$var integer 32 ( pass_count [31:0] $end
$var integer 32 ) fail_count [31:0] $end
$scope module DUT $end
$var wire 16 * A [15:0] $end
$var wire 16 + B [15:0] $end
$var wire 1 , Cin $end
$var wire 16 $ Sum [15:0] $end
$var wire 1 % Cout $end
$var wire 4 - block_P [3:0] $end
$var wire 4 . block_G [3:0] $end
$var wire 5 / C [4:0] $end
$scope module CLA0 $end
$var wire 4 0 A [3:0] $end
$var wire 4 1 B [3:0] $end
$var wire 1 2 Cin $end
$var wire 4 3 Sum [3:0] $end
$var wire 1 4 Cout $end
$var wire 1 5 P $end
$var wire 1 6 G $end
$var wire 4 7 p [3:0] $end
$var wire 4 8 g [3:0] $end
$var wire 5 9 c [4:0] $end
$upscope $end
$scope module CLA1 $end
$var wire 4 : A [7:4] $end
$var wire 4 ; B [7:4] $end
$var wire 1 < Cin $end
$var wire 4 = Sum [7:4] $end
$var wire 1 > Cout $end
$var wire 1 ? P $end
$var wire 1 @ G $end
$var wire 4 A p [3:0] $end
$var wire 4 B g [3:0] $end
$var wire 5 C c [4:0] $end
$upscope $end
$scope module CLA2 $end
$var wire 4 D A [11:8] $end
$var wire 4 E B [11:8] $end
$var wire 1 F Cin $end
$var wire 4 G Sum [11:8] $end
$var wire 1 H Cout $end
$var wire 1 I P $end
$var wire 1 J G $end
$var wire 4 K p [3:0] $end
$var wire 4 L g [3:0] $end
$var wire 5 M c [4:0] $end
$upscope $end
$scope module CLA3 $end
$var wire 4 N A [15:12] $end
$var wire 4 O B [15:12] $end
$var wire 1 P Cin $end
$var wire 4 Q Sum [15:12] $end
$var wire 1 R Cout $end
$var wire 1 S P $end
$var wire 1 T G $end
$var wire 4 U p [3:0] $end
$var wire 4 V g [3:0] $end
$var wire 5 W c [4:0] $end
$upscope $end
$upscope $end
$scope task check_result $end
$var reg 16 X test_A [15:0] $end
$var reg 16 Y test_B [15:0] $end
$var reg 1 Z test_Cin $end
$upscope $end
$upscope $end
$enddefinitions $end

#0
$dumpvars
b0 !
b0 "
0#
b0 $
0%
bx &
bx '
b0 (
b0 )
b0 *
b0 +
0,
b0 -
b0 .
b0 /
b0 0
b0 1
02
b0 3
04
05
06
b0 7
b0 8
b0 9
b0 :
b0 ;
0<
b0 =
0>
0?
0@
b0 A
b0 B
b0 C
b0 D
b0 E
0F
b0 G
0H
0I
0J
b0 K
b0 L
b0 M
b0 N
b0 O
0P
b0 Q
0R
0S
0T
b0 U
b0 V
b0 W
b0 X
b0 Y
0Z
$end

#10000
1#
b1 $
b0 &
b1 (
1,
b1 /
12
b1 3
b1 9
1Z

#20000
b1 !
b1 "
0#
b10 $
b1 &
b10 (
b1 *
b1 +
0,
b0 /
b1 0
b1 1
02
b10 3
b1 8
b10 9
b0 :
b0 ;
b0 D
b0 E
b0 N
b0 O
b1 X
b1 Y
0Z

#30000
b1111111111111111 !
b0 $
1%
b10 &
b11 (
b1111111111111111 *
b1110 -
b1 .
b11110 /
b1111 0
b0 3
14
16
b1110 7
b11110 9
b1111 :
1<
b0 =
1>
1?
b1111 A
b11111 C
b1111 D
1F
b0 G
1H
1I
b1111 K
b11111 M
b1111 N
1P
b0 Q
1R
1S
b1111 U
b11111 W
b1111111111111111 X

#40000
b1111111111111111 "
b1111111111111110 $
b10000000000000000 &
b100 (
b1111111111111111 +
b0 -
b1111 .
b1111 1
b1110 3
b0 7
b1111 8
b1111 ;
b1111 =
0?
1@
b0 A
b1111 B
b1111 E
b1111 G
0I
1J
b0 K
b1111 L
b1111 O
b1111 Q
0S
1T
b0 U
b1111 V
b1111111111111111 Y

#50000
1#
b1111111111111111 $
b11111111111111110 &
b101 (
1,
b11111 /
12
b1111 3
b11111 9
1Z

#60000
b111111111111111 !
b1 "
0#
b1000000000000000 $
0%
b11111111111111111 &
b110 (
b111111111111111 *
b1 +
0,
b110 -
b1 .
b1110 /
b1111 0
b1 1
02
b0 3
b1110 7
b1 8
b11110 9
b1111 :
b0 ;
b0 =
1?
0@
b1111 A
b0 B
b1111 D
b0 E
b0 G
1I
0J
b1111 K
b0 L
b111 N
b0 O
b1000 Q
0R
0T
b111 U
b0 V
b1111 W
b111111111111111 X
b1 Y
0Z

#70000
b1000000000000000 !
b1000000000000000 "
b0 $
1%
b1000000000000000 &
b111 (
b1000000000000000 *
b1000000000000000 +
b0 -
b1000 .
b10000 /
b0 0
b0 1
b0 3
04
06
b0 7
b0 8
b0 9
b0 :
b0 ;
0<
b0 =
0>
0?
b0 A
b0 C
b0 D
b0 E
0F
b0 G
0H
0I
b0 K
b0 M
b1000 N
b1000 O
0P
b0 Q
1R
1T
b0 U
b1000 V
b10000 W
b1000000000000000 X
b1000000000000000 Y

#80000
b111111111111 !
b1 "
b1000000000000 $
0%
b10000000000000000 &
b1000 (
b111111111111 *
b1 +
b110 -
b1 .
b1110 /
b1111 0
b1 1
b0 3
14
16
b1110 7
b1 8
b11110 9
b1111 :
b0 ;
1<
b0 =
1>
1?
b1111 A
b11111 C
b1111 D
b0 E
1F
b0 G
1H
1I
b1111 K
b11111 M
b0 N
b0 O
1P
b1 Q
0R
0T
b0 V
b1 W
b111111111111 X
b1 Y

#90000
b11111111 !
b100000000 $
b1000000000000 &
b1001 (
b11111111 *
b10 -
b110 /
b1111 0
b1111 :
b0 D
b1 G
0H
0I
b0 K
b1 M
b0 N
0P
b0 Q
b0 W
b11111111 X

#100000
b101010101010101 !
b1010101010101010 "
b1111111111111111 $
b100000000 &
b1010 (
b101010101010101 *
b1010101010101010 +
b1111 -
b0 .
b0 /
b101 0
b1010 1
b1111 3
04
15
06
b1111 7
b0 8
b0 9
b101 :
b1010 ;
0<
b1111 =
0>
b0 C
b101 D
b1010 E
0F
b1111 G
0H
1I
b1111 K
b0 M
b101 N
b1010 O
b1111 Q
1S
b1111 U
b101010101010101 X
b1010101010101010 Y

#110000
b1010101010101010 !
b101010101010101 "
1#
b0 $
1%
b1111111111111111 &
b1011 (
b1010101010101010 *
b101010101010101 +
1,
b11111 /
b1010 0
b101 1
12
b0 3
14
b11111 9
b1010 :
b101 ;
1<
b0 =
1>
b11111 C
b1010 D
b101 E
1F
b0 G
1H
b11111 M
b1010 N
b101 O
1P
b0 Q
1R
b11111 W
b1010101010101010 X
b101010101010101 Y
1Z

#120000
b1000100010001 !
b1110111011101110 "
0#
b1111111111111111 $
0%
b10000000000000000 &
b1100 (
b1000100010001 *
b1110111011101110 +
0,
b0 /
b1 0
b1110 1
02
b1111 3
04
b0 9
b1 :
b1110 ;
0<
b1111 =
0>
b0 C
b1 D
b1110 E
0F
b1111 G
0H
b0 M
b1 N
b1110 O
0P
b1111 Q
0R
b0 W
b1000100010001 X
b1110111011101110 Y
0Z

#130000
b1111111111111111 !
b0 "
1#
b0 $
1%
b1111111111111111 &
b1101 (
b1111111111111111 *
b0 +
1,
b11111 /
b1111 0
b0 1
12
b0 3
14
b11111 9
b1111 :
b0 ;
1<
b0 =
1>
b11111 C
b1111 D
b0 E
1F
b0 G
1H
b11111 M
b1111 N
b0 O
1P
b0 Q
1R
b11111 W
b1111111111111111 X
b0 Y
1Z

#140000
b11010100100100 !
b101111010000001 "
b1001001110100110 $
0%
b10000000000000000 &
b0 '
b1110 (
b11010100100100 *
b101111010000001 +
b0 -
b100 .
b1001 /
b100 0
b1 1
b110 3
04
05
b101 7
b11 9
b10 :
b1000 ;
0<
b1010 =
0>
0?
b1010 A
b0 C
b101 D
b1110 E
0F
b11 G
0I
1J
b1011 K
b100 L
b11000 M
b11 N
b101 O
b1001 Q
0R
0S
b110 U
b1 V
b1111 W
b11010100100100 X
b101111010000001 Y

#150000
b101011001100011 !
b111101100001101 "
b1101000101110001 $
b1001001110100110 &
b1 '
b1111 (
b101011001100011 *
b111101100001101 +
b101 .
b1011 /
b11 0
b1101 1
b1 3
14
16
b1110 7
b1 8
b11111 9
b110 :
b0 ;
1<
b111 =
b110 A
b1 C
b110 D
b1011 E
b1 G
b1101 K
b10 L
b11100 M
b101 N
b111 O
b1101 Q
b10 U
b101 V
b101011001100011 X
b111101100001101 Y

#160000
b1000010001100101 !
b101001000010010 "
b1101011001111000 $
b1101000101110001 &
b10 '
b10000 (
b1000010001100101 *
b101001000010010 +
b0 .
b1 /
b101 0
b10 1
b1000 3
04
06
b111 7
b0 8
b1111 9
b110 :
b1 ;
0<
b111 =
b111 A
b0 C
b100 D
b10 E
b110 G
0H
0J
b110 K
b0 L
b0 M
b1000 N
b101 O
0P
b1101 Q
b1101 U
b0 V
b0 W
b1000010001100101 X
b101001000010010 Y

#170000
b1100110100001101 !
b1111000101110110 "
b1011111010000100 $
1%
b1101011001111000 &
b11 '
b10001 (
b1100110100001101 *
b1111000101110110 +
b1001 .
b10011 /
b1101 0
b110 1
b100 3
14
16
b1011 7
b100 8
b11111 9
b0 :
b111 ;
1<
b1000 =
b1111 C
b1101 D
b1 E
b1110 G
b1100 K
b1 L
b10 M
b1100 N
b1111 O
b1011 Q
1R
1T
b11 U
b1100 V
b11000 W
b1100110100001101 X
b1111000101110110 Y

#180000
b101011111101101 !
b1111011110001100 "
b100111101111010 $
b11011111010000100 &
b100 '
b10010 (
b101011111101101 *
b1111011110001100 +
b1011 .
b10111 /
b1101 0
b1100 1
b1010 3
b1 7
b1100 8
b11011 9
b1110 :
b1000 ;
b111 =
1>
1@
b110 A
b1000 B
b10001 C
b111 D
b111 E
1F
b1111 G
b0 K
b111 L
b1111 M
b101 N
b1111 O
b100 Q
b1010 U
b101 V
b11110 W
b101011111101101 X
b1111011110001100 Y

#190000
b10010011000110 !
b1000010011000101 "
0#
b1010100110001011 $
0%
b10100111101111010 &
b101 '
b10011 (
b10010011000110 *
b1000010011000101 +
0,
b10 .
b100 /
b110 0
b101 1
02
b1011 3
04
06
b11 7
b100 8
b1000 9
b1100 :
b1100 ;
0<
b1000 =
b0 A
b1100 B
b11000 C
b100 D
b100 E
b1001 G
b100 L
b1001 M
b10 N
b1000 O
b1010 Q
0R
0T
b0 V
b0 W
b10010011000110 X
b1000010011000101 Y
0Z

#200000
b1111011111100101 !
b111001001110111 "
b110101001011100 $
1%
b1010100110001011 &
b110 '
b10100 (
b1111011111100101 *
b111001001110111 +
b1010 .
b10100 /
b101 0
b111 1
b1100 3
b10 7
b101 8
b1110 9
b1110 :
b111 ;
b101 =
b1001 A
b110 B
b11100 C
b111 D
b10 E
b1010 G
b101 K
b10 L
b1111 M
b1111 N
b111 O
b110 Q
1R
1T
b1000 U
b111 V
b11110 W
b1111011111100101 X
b111001001110111 Y

#210000
b1101101110001111 !
b110100111110010 "
b100010110000001 $
b10110101001011100 &
b111 '
b10101 (
b1101101110001111 *
b110100111110010 +
b1111 .
b11110 /
b1111 0
b10 1
b1 3
14
16
b1101 7
b10 8
b11100 9
b1000 :
b1111 ;
1<
b1000 =
b111 A
b1000 B
b11111 C
b1011 D
b1001 E
b101 G
1H
1J
b10 K
b1001 L
b10111 M
b1101 N
b110 O
1P
b100 Q
b1011 U
b100 V
b11111 W
b1101101110001111 X
b110100111110010 Y

#220000
b111101011101000 !
b100111011000101 "
b1100100110101101 $
0%
b10100010110000001 &
b1000 '
b10110 (
b111101011101000 *
b100111011000101 +
b110 .
b1100 /
b1000 0
b101 1
b1101 3
04
06
b0 8
b0 9
b1110 :
b1100 ;
0<
b1010 =
b10 A
b1100 B
b11000 C
b1010 D
b1110 E
b1001 G
b100 K
b1010 L
b11101 M
b111 N
b100 O
b1100 Q
0R
0T
b11 U
b1111 W
b111101011101000 X
b100111011000101 Y

#230000
b10100010111101 !
b101100000101101 "
1#
b1000000011101011 $
b1100100110101101 &
b1001 '
b10111 (
b10100010111101 *
b101100000101101 +
1,
b101 .
b1011 /
b1101 0
b1101 1
12
b1011 3
14
16
b0 7
b1101 8
b11011 9
b1011 :
b10 ;
1<
b1110 =
0>
0@
b1001 A
b10 B
b111 C
b1000 D
b1000 E
0F
b0 G
b0 K
b1000 L
b10000 M
b10 N
b101 O
b1000 Q
b111 U
b0 V
b10100010111101 X
b101100000101101 Y
1Z

#240000
b110001001100011 !
b1000011100001010 "
0#
b1110100101101101 $
b1000000011101011 &
b1010 '
b11000 (
b110001001100011 *
b1000011100001010 +
0,
b0 .
b0 /
b11 0
b1010 1
02
b1101 3
04
06
b1001 7
b10 8
b100 9
b110 :
b0 ;
0<
b110 =
b110 A
b0 B
b0 C
b10 D
b111 E
b1001 G
0H
0J
b101 K
b10 L
b1100 M
b110 N
b1000 O
0P
b1110 Q
b1110 U
b0 W
b110001001100011 X
b1000011100001010 Y
0Z

#250000
b10000100100000 !
b100010110101010 "
1#
b110011011001011 $
b1110100101101101 &
b1011 '
b11001 (
b10000100100000 *
b100010110101010 +
1,
b1 /
b0 0
b1010 1
12
b1011 3
b1010 7
b0 8
b1 9
b10 :
b1010 ;
b1100 =
b1000 A
b10 B
b100 C
b1 D
b101 E
b110 G
b100 K
b1 L
b10 M
b10 N
b100 O
b110 Q
b110 U
b10000100100000 X
b100010110101010 Y
1Z

#260000
b11111010010110 !
b1011100000010011 "
b1111011010101010 $
b110011011001011 &
b1100 '
b11010 (
b11111010010110 *
b1011100000010011 +
b100 .
b1001 /
b110 0
b11 1
b1010 3
b101 7
b10 8
b1111 9
b1001 :
b1 ;
b1010 =
b1 B
b10 C
b1110 D
b1000 E
b110 G
1H
1J
b110 K
b1000 L
b10000 M
b11 N
b1011 O
1P
b1111 Q
b1000 U
b11 V
b111 W
b11111010010110 X
b1011100000010011 Y

#270000
b1101011001010011 !
b1101110101101011 "
b1011001110111111 $
1%
b1111011010101010 &
b1101 '
b11011 (
b1101011001010011 *
b1101110101101011 +
b1100 .
b11001 /
b11 0
b1011 1
b1111 3
b1000 7
b11 8
b111 9
b101 :
b110 ;
b1011 =
b11 A
b100 B
b1000 C
b110 D
b1101 E
b11 G
b1011 K
b100 L
b11000 M
b1101 N
b1101 O
b1011 Q
1R
1T
b0 U
b1101 V
b11011 W
b1101011001010011 X
b1101110101101011 Y

#280000
b100101000000010 !
b11111010101110 "
b1000100010110001 $
0%
b11011001110111111 &
b1110 '
b11100 (
b100101000000010 *
b11111010101110 +
b101 .
b1011 /
b10 0
b1110 1
b1 3
14
16
b1100 7
b10 8
b11101 9
b0 :
b1010 ;
1<
b1011 =
b1010 A
b0 B
b1 C
b1010 D
b1110 E
b1000 G
b100 K
b1010 L
b11100 M
b100 N
b11 O
b1000 Q
0R
0T
b111 U
b0 V
b1111 W
b100101000000010 X
b11111010101110 Y

#290000
b111001011001111 !
b100100100100011 "
0#
b1011101111110010 $
b1000100010110001 &
b1111 '
b11101 (
b111001011001111 *
b100100100100011 +
0,
b1 .
b10 /
b1111 0
b11 1
02
b10 3
b11 8
b11110 9
b1100 :
b10 ;
b1111 =
b1110 A
b10 D
b1001 E
b1011 G
0H
0J
b1011 K
b0 L
b0 M
b111 N
b100 O
0P
b1011 Q
b11 U
b100 V
b1000 W
b111001011001111 X
b100100100100011 Y
0Z

#300000
b101011001010 !
b100110000111100 "
b101011100000110 $
b1011101111110010 &
b10000 '
b11110 (
b101011001010 *
b100110000111100 +
b10 -
b101 .
b1110 /
b1010 0
b1100 1
b110 3
b110 7
b1000 8
b10000 9
b1100 :
b11 ;
b0 =
1>
1?
b1111 A
b11111 C
b1010 D
b1100 E
1F
b111 G
1H
1J
b110 K
b1000 L
b10001 M
b0 N
b100 O
1P
b101 Q
b100 U
b0 V
b1 W
b101011001010 X
b100110000111100 Y

#310000
b110000110001010 !
b1011001101000001 "
b1010011001011 $
1%
b101011100000110 &
b10001 '
b11111 (
b110000110001010 *
b1011001101000001 +
b0 -
b1000 .
b10000 /
b1010 0
b1 1
b1011 3
04
06
b1011 7
b0 8
b0 9
b1000 :
b100 ;
0<
b1100 =
0>
0?
b1100 A
b0 C
b1 D
b11 E
0F
b100 G
0H
0J
b10 K
b1 L
b110 M
b110 N
b1011 O
0P
b1 Q
1R
1T
b1101 U
b10 V
b11100 W
b110000110001010 X
b1011001101000001 Y

#320000
b1111001101111000 !
b1001010001001 "
1#
b11000000010 $
b10001010011001011 &
b10010 '
b100000 (
b1111001101111000 *
b1001010001001 +
1,
b10 -
b1001 .
b10111 /
b1000 0
b1001 1
12
b10 3
14
16
b1 7
b1000 8
b10011 9
b111 :
b1000 ;
1<
b0 =
1>
1?
b1111 A
b11111 C
b11 D
b10 E
1F
b110 G
b1 K
b10 L
b111 M
b1111 N
b1 O
b0 Q
b1110 U
b1 V
b11110 W
b1111001101111000 X
b1001010001001 Y
1Z

#330000
b110010110110110 !
b1111100111000110 "
0#
b101111101111100 $
b10000011000000010 &
b10011 '
b100001 (
b110010110110110 *
b1111100111000110 +
0,
b0 -
b1010 .
b10100 /
b110 0
b110 1
02
b1100 3
04
06
b0 7
b110 8
b1100 9
b1011 :
b1100 ;
0<
b111 =
0?
1@
b111 A
b1000 B
b10000 C
b101 D
b1001 E
b1111 G
b1100 K
b1 L
b11 M
b110 N
b1111 O
b101 Q
b1001 U
b110 V
b11100 W
b110010110110110 X
b1111100111000110 Y
0Z

#340000
b1010111100 !
b1101110100101010 "
1#
b1101111111100111 $
0%
b10101111101111100 &
b10100 '
b100010 (
b1010111100 *
b1101110100101010 +
1,
b100 -
b1 .
b11 /
b1100 0
b1010 1
12
b111 3
14
16
b110 7
b1000 8
b10001 9
b1011 :
b10 ;
1<
b1110 =
0>
0@
b1001 A
b10 B
b111 C
b10 D
b1101 E
0F
b1111 G
0H
1I
b1111 K
b0 L
b0 M
b0 N
b1101 O
b1101 Q
0R
0T
b1101 U
b0 V
b0 W
b1010111100 X
b1101110100101010 Y
1Z

#350000
b1011111001110001 !
b100000110000101 "
b1111111111110111 $
b1101111111100111 &
b10101 '
b100011 (
b1011111001110001 *
b100000110000101 +
b1110 -
b0 .
b1 /
b1 0
b101 1
b111 3
04
06
b100 7
b1 8
b11 9
b111 :
b1000 ;
0<
b1111 =
0>
1?
b1111 A
b0 B
b0 C
b1110 D
b1 E
b1011 N
b100 O
b1111 Q
1S
b1111 U
b1011111001110001 X
b100000110000101 Y

#360000
b110000000111011 !
b11001100111010 "
0#
b1001001101110101 $
b1111111111110111 &
b10110 '
b100100 (
b110000000111011 *
b11001100111010 +
0,
b0 -
b1 .
b10 /
b1011 0
b1010 1
02
b101 3
14
16
b1 7
b1010 8
b10100 9
b11 :
b11 ;
1<
b111 =
0?
b0 A
b11 B
b111 C
b0 D
b11 E
b11 G
0I
b11 K
b110 N
b11 O
b1001 Q
0S
b101 U
b10 V
b1100 W
b110000000111011 X
b11001100111010 Y
0Z

#370000
b100101100010101 !
b1001101111110001 "
1#
b1110011100000111 $
b1001001101110101 &
b10111 '
b100101 (
b100101100010101 *
b1001101111110001 +
1,
b110 .
b1101 /
b101 0
b1 1
12
b111 3
04
06
b100 7
b1 8
b11 9
b1 :
b1111 ;
0<
b0 =
1>
1@
b1110 A
b1 B
b11110 C
b1011 D
b1011 E
1F
b111 G
1H
1J
b0 K
b1011 L
b10111 M
b100 N
b1001 O
1P
b1110 Q
b1101 U
b0 V
b11 W
b100101100010101 X
b1001101111110001 Y
1Z

#380000
b11101100010 !
b1111101101001100 "
b1010101111 $
1%
b1110011100000111 &
b11000 '
b100110 (
b11101100010 *
b1111101101001100 +
b1000 -
b100 .
b11001 /
b10 0
b1100 1
b1111 3
b1110 7
b0 8
b1 9
b110 :
b100 ;
b1010 =
0>
0@
b10 A
b100 B
b1000 C
b111 D
b1011 E
0F
b10 G
b1100 K
b11 L
b11110 M
b0 N
b1111 O
b0 Q
1R
1S
b1111 U
b11111 W
b11101100010 X
b1111101101001100 Y

#390000
b1010000110001111 !
b1010100111111000 "
b100101110001000 $
b10000001010101111 &
b11001 '
b100111 (
b1010000110001111 *
b1010100111111000 +
b0 -
b1011 .
b10111 /
b1111 0
b1000 1
b1000 3
14
16
b111 7
b1000 8
b11111 9
b1000 :
b1111 ;
1<
b1000 =
1>
1@
b111 A
b1000 B
b11111 C
b1 D
b1001 E
1F
b1011 G
0H
0J
b1000 K
b1 L
b11 M
b1010 N
b1010 O
0P
b100 Q
0S
1T
b0 U
b1010 V
b10100 W
b1010000110001111 X
b1010100111111000 Y

#400000
b101011010011111 !
b1001010001011100 "
b1110101011111100 $
0%
b10100101110001000 &
b11010 '
b101000 (
b101011010011111 *
b1001010001011100 +
b1 .
b11 /
b1111 0
b1100 1
b1100 3
b11 7
b1100 8
b1001 :
b101 ;
b1111 =
0>
0@
b1100 A
b1 B
b11 C
b110 D
b100 E
0F
b1010 G
b10 K
b100 L
b1000 M
b101 N
b1001 O
b1110 Q
0R
0T
b1100 U
b1 V
b10 W
b101011010011111 X
b1001010001011100 Y

#410000
b11011110001001 !
b11001001001001 "
0#
b110100111010010 $
b1110101011111100 &
b11011 '
b101001 (
b11011110001001 *
b11001001001001 +
0,
b10 /
b1001 0
b1001 1
02
b10 3
b0 7
b1001 8
b10010 9
b1000 :
b100 ;
b1101 =
b0 B
b1 C
b111 D
b10 E
b1001 G
b101 K
b10 L
b1100 M
b11 N
b11 O
b110 Q
b0 U
b11 V
b110 W
b11011110001001 X
b11001001001001 Y
0Z

#420000
b1100000011010111 !
b1111110001010001 "
b1011110100101000 $
1%
b110100111010010 &
b11100 '
b101010 (
b1100000011010111 *
b1111110001010001 +
b1010 .
b10100 /
b111 0
b1 1
b1000 3
04
06
b110 7
b1 8
b1110 9
b1101 :
b101 ;
0<
b10 =
1>
1@
b1000 A
b101 B
b11010 C
b0 D
b1100 E
1F
b1101 G
b1100 K
b0 L
b1 M
b1100 N
b1111 O
b1011 Q
1R
1T
b11 U
b1100 V
b11000 W
b1100000011010111 X
b1111110001010001 Y

#430000
b111111100001100 !
b1100111011000010 "
b100110111001110 $
b11011110100101000 &
b11101 '
b101011 (
b111111100001100 *
b1100111011000010 +
b1100 .
b11000 /
b1100 0
b10 1
b1110 3
b1110 7
b0 8
b0 9
b0 :
b1100 ;
b1100 =
0>
0@
b1100 A
b0 B
b0 C
b1111 D
b1110 E
0F
b1101 G
1H
1J
b1 K
b1110 L
b11100 M
b111 N
b1100 O
1P
b100 Q
b1011 U
b100 V
b11111 W
b111111100001100 X
b1100111011000010 Y

#440000
b101101001110111 !
b1110110100111101 "
b100011110110100 $
b10100110111001110 &
b11110 '
b101100 (
b101101001110111 *
b1110110100111101 +
b1101 .
b11010 /
b111 0
b1101 1
b100 3
14
16
b1010 7
b101 8
b11110 9
b111 :
b11 ;
1<
b1011 =
b100 A
b11 B
b1111 C
b1010 D
b1101 E
b111 G
b111 K
b1000 L
b10000 M
b101 N
b1110 O
b101101001110111 X
b1110110100111101 Y

#450000
b1111110 !
b1000000101101101 "
1#
b1000000111101100 $
0%
b10100011110110100 &
b11111 '
b101101 (
b1111110 *
b1000000101101101 +
1,
b1 .
b11 /
b1110 0
b1101 1
12
b1100 3
b11 7
b1100 8
b11111 9
b111 :
b110 ;
b1110 =
b1 A
b110 B
b0 D
b1 E
b1 G
0H
0J
b1 K
b0 L
b0 M
b0 N
b1000 O
0P
b1000 Q
0R
0T
b1000 U
b0 V
b0 W
b1111110 X
b1000000101101101 Y
1Z

#460000
b1000111100011111 !
b1111011011010011 "
b1000010111110011 $
1%
b1000000111101100 &
b100000 '
b101110 (
b1000111100011111 *
b1111011011010011 +
b1101 .
b11011 /
b1111 0
b11 1
b11 3
b1100 7
b11 8
b1 :
b1101 ;
b1111 =
b1100 A
b1 B
b11 C
b1111 D
b110 E
b101 G
1H
1J
b1001 K
b110 L
b11100 M
b1000 N
b1111 O
1P
b1000 Q
1R
1T
b111 U
b1000 V
b11111 W
b1000111100011111 X
b1111011011010011 Y

#470000
b1000100001111000 !
b101100101011011 "
b1110000111010100 $
0%
b11000010111110011 &
b100001 '
b101111 (
b1000100001111000 *
b101100101011011 +
b101 .
b1011 /
b1000 0
b1011 1
b100 3
b11 7
b1000 8
b10111 9
b111 :
b101 ;
b1101 =
b10 A
b101 B
b1111 C
b1000 D
b1001 E
b1 G
b1 K
b1000 L
b10000 M
b1000 N
b101 O
b1110 Q
0R
0T
b1101 U
b0 V
b11 W
b1000100001111000 X
b101100101011011 Y

