Sequential_Shift-and-Add_Multiplier/Sequential_Shift-and-Add_Multiplier.srcs/sources_1/new/sequential_shift_add_multiplier.v
module sequential_shift_add_multiplier (
    input wire clk,
    input wire reset,
    input wire start,
    input wire [15:0] multiplicand,
    input wire [15:0] multiplier,

    output reg [31:0] product,
    output reg done
);

    reg [31:0] accumulator;
    reg [31:0] multiplicand_reg;
    reg [15:0] multiplier_reg;
    reg [4:0] count;
    reg busy;

    wire [31:0] sum;

    // Add the multiplicand when the current multiplier bit is 1
    assign sum = multiplier_reg[0] ?
                 accumulator + multiplicand_reg :
                 accumulator;

    always @(posedge clk) begin
        if (reset) begin
            accumulator     <= 32'd0;
            multiplicand_reg <= 32'd0;
            multiplier_reg  <= 16'd0;
            count            <= 5'd0;
            product           <= 32'd0;
            busy              <= 1'b0;
            done              <= 1'b0;
        end
        else begin
            // done is asserted for one clock cycle
            done <= 1'b0;

            if (!busy) begin
                if (start) begin
                    // Load operands and initialize multiplication
                    accumulator      <= 32'd0;
                    multiplicand_reg <= {16'd0, multiplicand};
                    multiplier_reg   <= multiplier;
                    count             <= 5'd0;
                    busy              <= 1'b1;
                end
            end
            else begin
                // Perform one shift-and-add iteration
                accumulator      <= sum;
                multiplicand_reg <= multiplicand_reg << 1;
                multiplier_reg   <= multiplier_reg >> 1;
                count             <= count + 1'b1;

                // Finish after 16 iterations
                if (count == 5'd15) begin
                    product <= sum;
                    done    <= 1'b1;
                    busy    <= 1'b0;
                end
            end
        end
    end

endmodule

Sequential_Shift-and-Add_Multiplier/Sequential_Shift-and-Add_Multiplier.srcs/sim_1/new/tb_sequential_shift_add_multiplier.v
`timescale 1ns / 1ps

module tb_sequential_shift_add_multiplier;

    reg clk;
    reg reset;
    reg start;
    reg [15:0] multiplicand;
    reg [15:0] multiplier;

    wire [31:0] product;
    wire done;

    reg [31:0] expected;
    integer i;
    integer cycles;
    integer pass_count;
    integer fail_count;

    // Instantiate DUT
    sequential_shift_add_multiplier uut (
        .clk(clk),
        .reset(reset),
        .start(start),
        .multiplicand(multiplicand),
        .multiplier(multiplier),
        .product(product),
        .done(done)
    );

    // Clock generation: 10 ns period
    initial begin
        clk = 1'b0;
        forever #5 clk = ~clk;
    end

    // Task to apply and verify one multiplication
    task test_multiply;
        input [15:0] a;
        input [15:0] b;
        begin
            // Apply inputs on the falling edge
            @(negedge clk);
            multiplicand = a;
            multiplier = b;
            start = 1'b1;

            expected = {16'd0, a} * {16'd0, b};

            // Load operands
            @(negedge clk);
            start = 1'b0;

            // Wait for completion, with a timeout
            cycles = 0;
            while (done !== 1'b1 && cycles < 17) begin
                @(posedge clk);
                #1;
                cycles = cycles + 1;
            end

            // Check the result
            if (done === 1'b1 && product === expected) begin
                $display("PASS: %0d * %0d = %0d (cycles = %0d)",
                         a, b, product, cycles);
                pass_count = pass_count + 1;
            end
            else begin
                $display("FAIL: %0d * %0d | Expected = %0d, Got = %0d, Done = %b",
                         a, b, expected, product, done);
                fail_count = fail_count + 1;
            end

            // Allow the DUT to return to its idle state
            @(negedge clk);
        end
    endtask

    initial begin
        $dumpfile("sequential_multiplier.vcd");
        $dumpvars(0, tb_sequential_shift_add_multiplier);

        reset = 1'b1;
        start = 1'b0;
        multiplicand = 16'd0;
        multiplier = 16'd0;

        pass_count = 0;
        fail_count = 0;

        // Verify reset
        repeat (2) @(negedge clk);

        if (product === 32'd0 && done === 1'b0) begin
            $display("PASS: Reset verification");
            pass_count = pass_count + 1;
        end
        else begin
            $display("FAIL: Reset verification");
            fail_count = fail_count + 1;
        end

        reset = 1'b0;

        // Directed test cases
        test_multiply(16'd0,     16'd0);
        test_multiply(16'd0,     16'd65535);
        test_multiply(16'd1,     16'd1);
        test_multiply(16'd1,     16'd65535);
        test_multiply(16'd2,     16'd32768);
        test_multiply(16'd15,    16'd15);
        test_multiply(16'd255,   16'd255);
        test_multiply(16'd256,   16'd256);
        test_multiply(16'd32768, 16'd2);
        test_multiply(16'd65535, 16'd65535);
        test_multiply(16'hAAAA,  16'h5555);
        test_multiply(16'hFFFF,  16'h0001);

        // Randomized test cases
        for (i = 0; i < 20; i = i + 1) begin
            test_multiply($random, $random);
        end

        // Final summary
        $display("-----------------------------------");
        $display("Test Summary");
        $display("Passed: %0d", pass_count);
        $display("Failed: %0d", fail_count);
        $display("-----------------------------------");

        if (fail_count == 0)
            $display("ALL TESTS PASSED");
        else
            $display("SOME TESTS FAILED");

        $finish;
    end

endmodule

Sequential_Shift-and-Add_Multiplier/Sequential_Shift-and-Add_Multiplier.sim/sim_1/behav/xsim/sequential_multiplier.vcd
$date
   Tue Sep 29 19:55:40 2026
$end

$version
  2026.1
  $dumpfile ("sequential_multiplier.vcd") 
$end

$timescale
  1ps
$end

$scope module tb_sequential_shift_add_multiplier $end
$var reg 1 ! clk $end
$var reg 1 " reset $end
$var reg 1 # start $end
$var reg 16 $ multiplicand [15:0] $end
$var reg 16 % multiplier [15:0] $end
$var wire 32 & product [31:0] $end
$var wire 1 ' done $end
$var reg 32 ( expected [31:0] $end
$var integer 32 ) i [31:0] $end
$var integer 32 * cycles [31:0] $end
$var integer 32 + pass_count [31:0] $end
$var integer 32 , fail_count [31:0] $end
$scope module uut $end
$var wire 1 - clk $end
$var wire 1 . reset $end
$var wire 1 / start $end
$var wire 16 0 multiplicand [15:0] $end
$var wire 16 1 multiplier [15:0] $end
$var reg 32 2 product [31:0] $end
$var reg 1 3 done $end
$var reg 32 4 accumulator [31:0] $end
$var reg 32 5 multiplicand_reg [31:0] $end
$var reg 16 6 multiplier_reg [15:0] $end
$var reg 5 7 count [4:0] $end
$var reg 1 8 busy $end
$var wire 32 9 sum [31:0] $end
$upscope $end
$scope task test_multiply $end
$var reg 16 : a [15:0] $end
$var reg 16 ; b [15:0] $end
$upscope $end
$upscope $end
$enddefinitions $end

#0
$dumpvars
0!
1"
0#
b0 $
b0 %
bx &
x'
bx (
bx )
bx *
b0 +
b0 ,
0-
1.
0/
b0 0
b0 1
bx 2
x3
bx 4
bx 5
bx 6
bx 7
x8
bx 9
bx :
bx ;
$end

#5000
1!
b0 &
0'
1-
b0 2
03
b0 4
b0 5
b0 6
b0 7
08
b0 9

#10000
0!
0-

#15000
1!
1-

#20000
0!
0"
b1 +
0-
0.
b0 :
b0 ;

#25000
1!
1-

#30000
0!
1#
b0 (
0-
1/

#35000
1!
1-
18

#40000
0!
0#
b0 *
0-
0/

#45000
1!
1-
b1 7

#46000
b1 *

#50000
0!
0-

#55000
1!
1-
b10 7

#56000
b10 *

#60000
0!
0-

#65000
1!
1-
b11 7

#66000
b11 *

#70000
0!
0-

#75000
1!
1-
b100 7

#76000
b100 *

#80000
0!
0-

#85000
1!
1-
b101 7

#86000
b101 *

#90000
0!
0-

#95000
1!
1-
b110 7

#96000
b110 *

#100000
0!
0-

#105000
1!
1-
b111 7

#106000
b111 *

#110000
0!
0-

#115000
1!
1-
b1000 7

#116000
b1000 *

#120000
0!
0-

#125000
1!
1-
b1001 7

#126000
b1001 *

#130000
0!
0-

#135000
1!
1-
b1010 7

#136000
b1010 *

#140000
0!
0-

#145000
1!
1-
b1011 7

#146000
b1011 *

#150000
0!
0-

#155000
1!
1-
b1100 7

#156000
b1100 *

#160000
0!
0-

#165000
1!
1-
b1101 7

#166000
b1101 *

#170000
0!
0-

#175000
1!
1-
b1110 7

#176000
b1110 *

#180000
0!
0-

#185000
1!
1-
b1111 7

#186000
b1111 *

#190000
0!
0-

#195000
1!
1'
1-
13
b10000 7
08

#196000
b10000 *
b10 +

#200000
0!
0-
b1111111111111111 ;

#205000
1!
0'
1-
03

#210000
0!
1#
b1111111111111111 %
0-
1/
b1111111111111111 1

#215000
1!
1-
b1111111111111111 6
b0 7
18

#220000
0!
0#
b0 *
0-
0/

#225000
1!
1-
b111111111111111 6
b1 7

#226000
b1 *

#230000
0!
0-

#235000
1!
1-
b11111111111111 6
b10 7

#236000
b10 *

#240000
0!
0-

#245000
1!
1-
b1111111111111 6
b11 7

#246000
b11 *

#250000
0!
0-

#255000
1!
1-
b111111111111 6
b100 7

#256000
b100 *

#260000
0!
0-

#265000
1!
1-
b11111111111 6
b101 7

#266000
b101 *

#270000
0!
0-

#275000
1!
1-
b1111111111 6
b110 7

#276000
b110 *

#280000
0!
0-

#285000
1!
1-
b111111111 6
b111 7

#286000
b111 *

#290000
0!
0-

#295000
1!
1-
b11111111 6
b1000 7

#296000
b1000 *

#300000
0!
0-

#305000
1!
1-
b1111111 6
b1001 7

#306000
b1001 *

#310000
0!
0-

#315000
1!
1-
b111111 6
b1010 7

#316000
b1010 *

#320000
0!
0-

#325000
1!
1-
b11111 6
b1011 7

#326000
b1011 *

#330000
0!
0-

#335000
1!
1-
b1111 6
b1100 7

#336000
b1100 *

#340000
0!
0-

#345000
1!
1-
b111 6
b1101 7

#346000
b1101 *

#350000
0!
0-

#355000
1!
1-
b11 6
b1110 7

#356000
b1110 *

#360000
0!
0-

#365000
1!
1-
b1 6
b1111 7

#366000
b1111 *

#370000
0!
0-

#375000
1!
1'
1-
13
b0 6
b10000 7
08

#376000
b10000 *
b11 +

#380000
0!
0-
b1 :
b1 ;

#385000
1!
0'
1-
03

#390000
0!
1#
b1 $
b1 %
b1 (
0-
1/
b1 0
b1 1

#395000
1!
1-
b1 5
b1 6
b0 7
18
b1 9

#400000
0!
0#
b0 *
0-
0/

#405000
1!
1-
b1 4
b10 5
b0 6
b1 7

#406000
b1 *

#410000
0!
0-

#415000
1!
1-
b100 5
b10 7

#416000
b10 *

#420000
0!
0-

#425000
1!
1-
b1000 5
b11 7

#426000
b11 *

#430000
0!
0-

#435000
1!
1-
b10000 5
b100 7

#436000
b100 *

#440000
0!
0-

#445000
1!
1-
b100000 5
b101 7

#446000
b101 *

#450000
0!
0-

#455000
1!
1-
b1000000 5
b110 7

#456000
b110 *

#460000
0!
0-

#465000
1!
1-
b10000000 5
b111 7

#466000
b111 *

#470000
0!
0-

#475000
1!
1-
b100000000 5
b1000 7

#476000
b1000 *

#480000
0!
0-

#485000
1!
1-
b1000000000 5
b1001 7

#486000
b1001 *

#490000
0!
0-

#495000
1!
1-
b10000000000 5
b1010 7

#496000
b1010 *

#500000
0!
0-

#505000
1!
1-
b100000000000 5
b1011 7

#506000
b1011 *

#510000
0!
0-

#515000
1!
1-
b1000000000000 5
b1100 7

#516000
b1100 *

#520000
0!
0-

#525000
1!
1-
b10000000000000 5
b1101 7

#526000
b1101 *

#530000
0!
0-

#535000
1!
1-
b100000000000000 5
b1110 7

#536000
b1110 *

#540000
0!
0-

#545000
1!
1-
b1000000000000000 5
b1111 7

#546000
b1111 *

#550000
0!
0-

#555000
1!
b1 &
1'
1-
b1 2
13
b10000000000000000 5
b10000 7
08

#556000
b10000 *
b100 +

#560000
0!
0-
b1111111111111111 ;

#565000
1!
0'
1-
03

#570000
0!
1#
b1111111111111111 %
b1111111111111111 (
0-
1/
b1111111111111111 1

#575000
1!
1-
b0 4
b1 5
b1111111111111111 6
b0 7
18

#580000
0!
0#
b0 *
0-
0/

#585000
1!
1-
b1 4
b10 5
b111111111111111 6
b1 7
b11 9

#586000
b1 *

#590000
0!
0-

#595000
1!
1-
b11 4
b100 5
b11111111111111 6
b10 7
b111 9

#596000
b10 *

#600000
0!
0-

#605000
1!
1-
b111 4
b1000 5
b1111111111111 6
b11 7
b1111 9

#606000
b11 *

#610000
0!
0-

#615000
1!
1-
b1111 4
b10000 5
b111111111111 6
b100 7
b11111 9

#616000
b100 *

#620000
0!
0-

#625000
1!
1-
b11111 4
b100000 5
b11111111111 6
b101 7
b111111 9

#626000
b101 *

#630000
0!
0-

#635000
1!
1-
b111111 4
b1000000 5
b1111111111 6
b110 7
b1111111 9

#636000
b110 *

#640000
0!
0-

#645000
1!
1-
b1111111 4
b10000000 5
b111111111 6
b111 7
b11111111 9

#646000
b111 *

#650000
0!
0-

#655000
1!
1-
b11111111 4
b100000000 5
b11111111 6
b1000 7
b111111111 9

#656000
b1000 *

#660000
0!
0-

#665000
1!
1-
b111111111 4
b1000000000 5
b1111111 6
b1001 7
b1111111111 9

#666000
b1001 *

#670000
0!
0-

#675000
1!
1-
b1111111111 4
b10000000000 5
b111111 6
b1010 7
b11111111111 9

#676000
b1010 *

#680000
0!
0-

#685000
1!
1-
b11111111111 4
b100000000000 5
b11111 6
b1011 7
b111111111111 9

#686000
b1011 *

#690000
0!
0-

#695000
1!
1-
b111111111111 4
b1000000000000 5
b1111 6
b1100 7
b1111111111111 9

#696000
b1100 *

#700000
0!
0-

#705000
1!
1-
b1111111111111 4
b10000000000000 5
b111 6
b1101 7
b11111111111111 9

#706000
b1101 *

#710000
0!
0-

#715000
1!
1-
b11111111111111 4
b100000000000000 5
b11 6
b1110 7
b111111111111111 9

#716000
b1110 *

#720000
0!
0-

#725000
1!
1-
b111111111111111 4
b1000000000000000 5
b1 6
b1111 7
b1111111111111111 9

#726000
b1111 *

#730000
0!
0-

#735000
1!
b1111111111111111 &
1'
1-
b1111111111111111 2
13
b1111111111111111 4
b10000000000000000 5
b0 6
b10000 7
08

#736000
b10000 *
b101 +

#740000
0!
0-
b10 :
b1000000000000000 ;

#745000
1!
0'
1-
03

#750000
0!
1#
b10 $
b1000000000000000 %
b10000000000000000 (
0-
1/
b10 0
b1000000000000000 1

#755000
1!
1-
b0 4
b10 5
b1000000000000000 6
b0 7
18
b0 9

#760000
0!
0#
b0 *
0-
0/

#765000
1!
1-
b100 5
b100000000000000 6
b1 7

#766000
b1 *

#770000
0!
0-

#775000
1!
1-
b1000 5
b10000000000000 6
b10 7

#776000
b10 *

#780000
0!
0-

#785000
1!
1-
b10000 5
b1000000000000 6
b11 7

#786000
b11 *

#790000
0!
0-

#795000
1!
1-
b100000 5
b100000000000 6
b100 7

#796000
b100 *

#800000
0!
0-

#805000
1!
1-
b1000000 5
b10000000000 6
b101 7

#806000
b101 *

#810000
0!
0-

#815000
1!
1-
b10000000 5
b1000000000 6
b110 7

#816000
b110 *

#820000
0!
0-

#825000
1!
1-
b100000000 5
b100000000 6
b111 7

#826000
b111 *

#830000
0!
0-

#835000
1!
1-
b1000000000 5
b10000000 6
b1000 7

#836000
b1000 *

#840000
0!
0-

#845000
1!
1-
b10000000000 5
b1000000 6
b1001 7

#846000
b1001 *

#850000
0!
0-

#855000
1!
1-
b100000000000 5
b100000 6
b1010 7

#856000
b1010 *

#860000
0!
0-

#865000
1!
1-
b1000000000000 5
b10000 6
b1011 7

#866000
b1011 *

#870000
0!
0-

#875000
1!
1-
b10000000000000 5
b1000 6
b1100 7

#876000
b1100 *

#880000
0!
0-

#885000
1!
1-
b100000000000000 5
b100 6
b1101 7

#886000
b1101 *

#890000
0!
0-

#895000
1!
1-
b1000000000000000 5
b10 6
b1110 7

#896000
b1110 *

#900000
0!
0-

#905000
1!
1-
b10000000000000000 5
b1 6
b1111 7
b10000000000000000 9

#906000
b1111 *

#910000
0!
0-

#915000
1!
b10000000000000000 &
1'
1-
b10000000000000000 2
13
b10000000000000000 4
b100000000000000000 5
b0 6
b10000 7
08

#916000
b10000 *
b110 +

#920000
0!
0-
b1111 :
b1111 ;

#925000
1!
0'
1-
03

#930000
0!
1#
b1111 $
b1111 %
b11100001 (
0-
1/
b1111 0
b1111 1

#935000
1!
1-
b0 4
b1111 5
b1111 6
b0 7
18
b1111 9

#940000
0!
0#
b0 *
0-
0/

#945000
1!
1-
b1111 4
b11110 5
b111 6
b1 7
b101101 9

#946000
b1 *

#950000
0!
0-

#955000
1!
1-
b101101 4
b111100 5
b11 6
b10 7
b1101001 9

#956000
b10 *

#960000
0!
0-

#965000
1!
1-
b1101001 4
b1111000 5
b1 6
b11 7
b11100001 9

#966000
b11 *

#970000
0!
0-

#975000
1!
1-
b11100001 4
b11110000 5
b0 6
b100 7

#976000
b100 *

#980000
0!
0-

#985000
1!
1-
b111100000 5
b101 7

#986000
b101 *

#990000
0!
0-

#995000
1!
1-
b1111000000 5
b110 7

#996000
b110 *
