fp16_multiplier/fp16_multiplier.srcs/sources_1/new/fp16_multiplier.v
module fp16_multiplier (
    input  [15:0] a,
    input  [15:0] b,
    output reg [15:0] product
);

    // Field extraction
    reg        sign_result;
    reg [4:0]  exponent_a;
    reg [4:0]  exponent_b;
    reg [9:0]  fraction_a;
    reg [9:0]  fraction_b;

    // 11-bit significands: implicit leading 1 for normalized numbers
    reg [10:0] mantissa_a;
    reg [10:0] mantissa_b;

    // 22-bit multiplication result
    reg [21:0] mantissa_product;

    // Result exponent
    reg signed [6:0] exponent_result;

    reg [9:0] fraction_result;

    always @* begin

        // Extract fields
        sign_result = a[15] ^ b[15];

        exponent_a = a[14:10];
        exponent_b = b[14:10];

        fraction_a = a[9:0];
        fraction_b = b[9:0];

        // Default values
        product          = 16'b0;
        mantissa_a       = 11'b0;
        mantissa_b       = 11'b0;
        mantissa_product = 22'b0;
        exponent_result  = 7'sd0;
        fraction_result  = 10'b0;

        // ------------------------------------------------------------
        // Special case 1: NaN
        // Exponent = 31 and fraction != 0
        // ------------------------------------------------------------
        if (((exponent_a == 5'b11111) && (fraction_a != 10'b0)) ||
            ((exponent_b == 5'b11111) && (fraction_b != 10'b0))) begin

            product = 16'h7E00;   // Quiet NaN

        end

        // ------------------------------------------------------------
        // Special case 2: Infinity
        // Infinity * Zero = NaN
        // ------------------------------------------------------------
        else if ((exponent_a == 5'b11111) ||
                 (exponent_b == 5'b11111)) begin

            if ((exponent_a == 5'b00000) ||
                (exponent_b == 5'b00000)) begin

                product = 16'h7E00;   // NaN

            end
            else begin

                product = {sign_result, 5'b11111, 10'b0000000000};
            end
        end

        // ------------------------------------------------------------
        // Special case 3: Zero / subnormal input
        // For this simplified implementation, exponent = 0 is
        // treated as zero.
        // ------------------------------------------------------------
        else if ((exponent_a == 5'b00000) ||
                 (exponent_b == 5'b00000)) begin

            product = {sign_result, 15'b0};

        end

        // ------------------------------------------------------------
        // Normalized floating-point multiplication
        // ------------------------------------------------------------
        else begin

            // Add the implicit leading 1
            mantissa_a = {1'b1, fraction_a};
            mantissa_b = {1'b1, fraction_b};

            // 11-bit x 11-bit = 22-bit multiplication
            mantissa_product = mantissa_a * mantissa_b;

            // Exponent:
            // Ea + Eb - Bias
            exponent_result =
                $signed({2'b00, exponent_a}) +
                $signed({2'b00, exponent_b}) -
                7'sd15;

            // --------------------------------------------------------
            // Normalize the significand
            //
            // Product range is [1,4), so the product either:
            //   1.xxxxx -> no additional shift
            //   10.xxxx -> shift right by one and increment exponent
            // --------------------------------------------------------
            if (mantissa_product[21] == 1'b1) begin

                fraction_result = mantissa_product[20:11];
                exponent_result = exponent_result + 7'sd1;

            end
            else begin

                fraction_result = mantissa_product[19:10];

            end

            // --------------------------------------------------------
            // Overflow -> Infinity
            // --------------------------------------------------------
            if (exponent_result >= 7'sd31) begin

                product = {sign_result, 5'b11111, 10'b0};

            end

            // --------------------------------------------------------
            // Underflow -> Zero
            // --------------------------------------------------------
            else if (exponent_result <= 7'sd0) begin

                product = {sign_result, 15'b0};

            end

            // --------------------------------------------------------
            // Normal result
            // --------------------------------------------------------
            else begin

                product = {
                    sign_result,
                    exponent_result[4:0],
                    fraction_result
                };

            end
        end

    end

endmodule

fp16_multiplier/fp16_multiplier.srcs/sim_1/new/fp16_multiplier_tb.v
`timescale 1ns/1ps

module fp16_multiplier_tb;

    reg  [15:0] a;
    reg  [15:0] b;
    wire [15:0] product;

    integer test_count;
    integer pass_count;
    integer fail_count;

    // DUT
    fp16_multiplier dut (
        .a(a),
        .b(b),
        .product(product)
    );

    // ------------------------------------------------------------
    // Test task
    // ------------------------------------------------------------
    task apply_and_check;
        input [15:0] a_value;
        input [15:0] b_value;
        input [15:0] expected_value;

        begin
            a = a_value;
            b = b_value;

            // Allow combinational logic to settle
            #15;

            test_count = test_count + 1;

            if (product === expected_value) begin
                pass_count = pass_count + 1;

                $display(
                    "PASS: A=%h  B=%h  PRODUCT=%h",
                    a, b, product
                );
            end
            else begin
                fail_count = fail_count + 1;

                $display(
                    "FAIL: A=%h  B=%h  EXPECTED=%h  ACTUAL=%h",
                    a, b, expected_value, product
                );
            end
        end
    endtask

    initial begin

        // VCD waveform generation
        $dumpfile("fp16_multiplier.vcd");
        $dumpvars(0, fp16_multiplier_tb);

        // Counters
        test_count = 0;
        pass_count = 0;
        fail_count = 0;

        // Initial values
        a = 16'b0;
        b = 16'b0;

        #1;

        // --------------------------------------------------------
        // Basic multiplication
        // --------------------------------------------------------

        // 1.0 * 1.0 = 1.0
        apply_and_check(16'h3C00, 16'h3C00, 16'h3C00);

        // 1.0 * 2.0 = 2.0
        apply_and_check(16'h3C00, 16'h4000, 16'h4000);

        // 2.0 * 4.0 = 8.0
        apply_and_check(16'h4000, 16'h4400, 16'h4800);

        // 1.5 * 2.0 = 3.0
        apply_and_check(16'h3E00, 16'h4000, 16'h4200);

        // 1.5 * 1.25 = 1.875
        apply_and_check(16'h3E00, 16'h3D00, 16'h3F80);

        // 2.5 * 4.0 = 10.0
        apply_and_check(16'h4100, 16'h4400, 16'h4900);

        // --------------------------------------------------------
        // Sign tests
        // --------------------------------------------------------

        // -1.5 * 2.0 = -3.0
        apply_and_check(16'hBE00, 16'h4000, 16'hC200);

        // -2.0 * -4.0 = +8.0
        apply_and_check(16'hC000, 16'hC400, 16'h4800);

        // +2.0 * -4.0 = -8.0
        apply_and_check(16'h4000, 16'hC400, 16'hC800);

        // --------------------------------------------------------
        // Zero tests
        // --------------------------------------------------------

        // 0 * 1 = 0
        apply_and_check(16'h0000, 16'h3C00, 16'h0000);

        // 1 * 0 = 0
        apply_and_check(16'h3C00, 16'h0000, 16'h0000);

        // -0 * 1 = -0
        apply_and_check(16'h8000, 16'h3C00, 16'h8000);

        // --------------------------------------------------------
        // Boundary tests
        // --------------------------------------------------------

        // Maximum finite value * 1 = maximum finite value
        apply_and_check(16'h7BFF, 16'h3C00, 16'h7BFF);

        // 32768 * 2 -> overflow -> +Infinity
        apply_and_check(16'h7800, 16'h4000, 16'h7C00);

        // Negative overflow -> -Infinity
        apply_and_check(16'hF800, 16'h4000, 16'hFC00);

        // --------------------------------------------------------
        // Special values
        // --------------------------------------------------------

        // Infinity * 2 = Infinity
        apply_and_check(16'h7C00, 16'h4000, 16'h7C00);

        // -Infinity * 2 = -Infinity
        apply_and_check(16'hFC00, 16'h4000, 16'hFC00);

        // Infinity * 0 = NaN
        apply_and_check(16'h7C00, 16'h0000, 16'h7E00);

        // NaN * 1 = NaN
        apply_and_check(16'h7E00, 16'h3C00, 16'h7E00);

        // --------------------------------------------------------
        // Underflow / subnormal handling
        // --------------------------------------------------------

        // Smallest normal * 0.5 -> underflow to zero
        apply_and_check(16'h0400, 16'h3800, 16'h0000);

        // Exponent = 0 is treated as zero in this simplified design
        apply_and_check(16'h0001, 16'h3C00, 16'h0000);

        // --------------------------------------------------------
        // Final summary
        // --------------------------------------------------------

        $display("");
        $display("========================================");
        $display("16-bit Floating-Point Multiplier Test");
        $display("========================================");
        $display("Total Tests : %0d", test_count);
        $display("Passed      : %0d", pass_count);
        $display("Failed      : %0d", fail_count);

        if (fail_count == 0)
            $display("RESULT      : ALL TESTS PASSED");
        else
            $display("RESULT      : SOME TESTS FAILED");

        $display("========================================");

        $finish;
    end

endmodule

fp16_multiplier/fp16_multiplier.sim/sim_1/behav/xsim/fp16_multiplier.vcd
$date
   Wed Sep 30 16:10:56 2026
$end

$version
  2026.1
  $dumpfile ("fp16_multiplier.vcd") 
$end

$timescale
  1ps
$end

$scope module fp16_multiplier_tb $end
$var reg 16 ! a [15:0] $end
$var reg 16 " b [15:0] $end
$var wire 16 # product [15:0] $end
$var integer 32 $ test_count [31:0] $end
$var integer 32 % pass_count [31:0] $end
$var integer 32 & fail_count [31:0] $end
$scope module dut $end
$var wire 16 ' a [15:0] $end
$var wire 16 ( b [15:0] $end
$var reg 16 ) product [15:0] $end
$var reg 1 * sign_result $end
$var reg 5 + exponent_a [4:0] $end
$var reg 5 , exponent_b [4:0] $end
$var reg 10 - fraction_a [9:0] $end
$var reg 10 . fraction_b [9:0] $end
$var reg 11 / mantissa_a [10:0] $end
$var reg 11 0 mantissa_b [10:0] $end
$var reg 22 1 mantissa_product [21:0] $end
$var reg 7 2 exponent_result [6:0] $end
$var reg 10 3 fraction_result [9:0] $end
$upscope $end
$scope task apply_and_check $end
$var reg 16 4 a_value [15:0] $end
$var reg 16 5 b_value [15:0] $end
$var reg 16 6 expected_value [15:0] $end
$upscope $end
$upscope $end
$enddefinitions $end

#0
$dumpvars
b0 !
b0 "
b0 #
b0 $
b0 %
b0 &
b0 '
b0 (
b0 )
0*
b0 +
b0 ,
b0 -
b0 .
b0 /
b0 0
b0 1
b0 2
b0 3
bx 4
bx 5
bx 6
$end

#1000
b11110000000000 !
b11110000000000 "
b11110000000000 #
b11110000000000 '
b11110000000000 (
b11110000000000 )
b1111 +
b1111 ,
b10000000000 /
b10000000000 0
b100000000000000000000 1
b1111 2
b11110000000000 4
b11110000000000 5
b11110000000000 6

#2000
b100000000000000 "
b100000000000000 #
b1 $
b1 %
b100000000000000 (
b100000000000000 )
b10000 ,
b10000000000 /
b10000000000 0
b100000000000000000000 1
b10000 2
b100000000000000 5
b100000000000000 6

#3000
b100000000000000 !
b100010000000000 "
b100100000000000 #
b10 $
b10 %
b100000000000000 '
b100010000000000 (
b100100000000000 )
b10000 +
b10001 ,
b10000000000 /
b10000000000 0
b100000000000000000000 1
b10010 2
b100000000000000 4
b100010000000000 5
b100100000000000 6

#4000
b11111000000000 !
b100000000000000 "
b100001000000000 #
b11 $
b11 %
b11111000000000 '
b100000000000000 (
b100001000000000 )
b1111 +
b10000 ,
b1000000000 -
b11000000000 /
b10000000000 0
b110000000000000000000 1
b10000 2
b1000000000 3
b11111000000000 4
b100000000000000 5
b100001000000000 6

#5000
b11110100000000 "
b11111110000000 #
b100 $
b100 %
b11110100000000 (
b11111110000000 )
b1111 ,
b100000000 .
b11000000000 /
b10100000000 0
b111100000000000000000 1
b1111 2
b1110000000 3
b11110100000000 5
b11111110000000 6

#6000
b100000100000000 !
b100010000000000 "
b100100100000000 #
b101 $
b101 %
b100000100000000 '
b100010000000000 (
b100100100000000 )
b10000 +
b10001 ,
b100000000 -
b0 .
b10100000000 /
b10000000000 0
b101000000000000000000 1
b10010 2
b100000000 3
b100000100000000 4
b100010000000000 5
b100100100000000 6

#7000
b1011111000000000 !
b100000000000000 "
b1100001000000000 #
b110 $
b110 %
b1011111000000000 '
b100000000000000 (
b1100001000000000 )
1*
b1111 +
b10000 ,
b1000000000 -
b11000000000 /
b10000000000 0
b110000000000000000000 1
b10000 2
b1000000000 3
b1011111000000000 4
b100000000000000 5
b1100001000000000 6

#8000
b1100000000000000 !
b1100010000000000 "
b100100000000000 #
b111 $
b111 %
b1100000000000000 '
b1100010000000000 (
b100100000000000 )
0*
b10000 +
b10001 ,
b0 -
b10000000000 /
b10000000000 0
b100000000000000000000 1
b10010 2
b0 3
b1100000000000000 4
b1100010000000000 5
b100100000000000 6

#9000
b100000000000000 !
b1100100000000000 #
b1000 $
b1000 %
b100000000000000 '
b1100100000000000 )
1*
b10000000000 /
b10000000000 0
b100000000000000000000 1
b10010 2
b100000000000000 4
b1100100000000000 6

#10000
b0 !
b11110000000000 "
b0 #
b1001 $
b1001 %
b0 '
b11110000000000 (
b0 )
0*
b0 +
b1111 ,
b0 /
b0 0
b0 1
b0 2
b0 4
b11110000000000 5
b0 6

#11000
b11110000000000 !
b0 "
b1010 $
b1010 %
b11110000000000 '
b0 (
b1111 +
b0 ,
b11110000000000 4
b0 5

#12000
b1000000000000000 !
b11110000000000 "
b1000000000000000 #
b1011 $
b1011 %
b1000000000000000 '
b11110000000000 (
b1000000000000000 )
1*
b0 +
b1111 ,
b1000000000000000 4
b11110000000000 5
b1000000000000000 6

#13000
b111101111111111 !
b111101111111111 #
b1100 $
b1100 %
b111101111111111 '
b111101111111111 )
0*
b11110 +
b1111111111 -
b11111111111 /
b10000000000 0
b111111111110000000000 1
b11110 2
b1111111111 3
b111101111111111 4
b111101111111111 6

#14000
b111100000000000 !
b100000000000000 "
b111110000000000 #
b1101 $
b1101 %
b111100000000000 '
b100000000000000 (
b111110000000000 )
b10000 ,
b0 -
b10000000000 /
b10000000000 0
b100000000000000000000 1
b11111 2
b0 3
b111100000000000 4
b100000000000000 5
b111110000000000 6

#15000
b1111100000000000 !
b1111110000000000 #
b1110 $
b1110 %
b1111100000000000 '
b1111110000000000 )
1*
b10000000000 /
b10000000000 0
b100000000000000000000 1
b11111 2
b1111100000000000 4
b1111110000000000 6

#16000
b111110000000000 !
b111110000000000 #
b1111 $
b1111 %
b111110000000000 '
b111110000000000 )
0*
b11111 +
b0 /
b0 0
b0 1
b0 2
b111110000000000 4
b111110000000000 6

#17000
b1111110000000000 !
b1111110000000000 #
b10000 $
b10000 %
b1111110000000000 '
b1111110000000000 )
1*
b1111110000000000 4
b1111110000000000 6

#18000
b111110000000000 !
b0 "
b111111000000000 #
b10001 $
b10001 %
b111110000000000 '
b0 (
b111111000000000 )
0*
b0 ,
b111110000000000 4
b0 5
b111111000000000 6

#19000
b111111000000000 !
b11110000000000 "
b10010 $
b10010 %
b111111000000000 '
b11110000000000 (
b111111000000000 )
b1111 ,
b1000000000 -
b111111000000000 4
b11110000000000 5

#20000
b10000000000 !
b11100000000000 "
b0 #
b10011 $
b10011 %
b10000000000 '
b11100000000000 (
b0 )
b1 +
b1110 ,
b0 -
b10000000000 /
b10000000000 0
b100000000000000000000 1
b10000000000 4
b11100000000000 5
b0 6

#21000
b1 !
b11110000000000 "
b10100 $
b10100 %
b1 '
b11110000000000 (
b0 +
b1111 ,
b1 -
b0 /
b0 0
b0 1
b1 4
b11110000000000 5

#22000
b10101 $
b10101 %
