tree_multiplier_32/tree_multiplier_32.srcs/sources_1/new/tree_multiplier_32bit.v
`timescale 1ns / 1ps

module tree_multiplier_32bit (
    input  wire [31:0] multiplicand,
    input  wire [31:0] multiplier,
    output wire [63:0] product
);

    // ------------------------------------------------------------------------
    // Stage 0: Generate 32 partial products.
    // Each partial product is either zero or a shifted version
    // of the 32-bit multiplicand.
    // ------------------------------------------------------------------------
    wire [63:0] partial_product [0:31];

    genvar i;

    generate
        for (i = 0; i < 32; i = i + 1) begin : GEN_PARTIAL_PRODUCTS
            assign partial_product[i] =
                multiplier[i] ?
                ({32'b0, multiplicand} << i) :
                64'b0;
        end
    endgenerate

    // ------------------------------------------------------------------------
    // Stage 1: 32 partial products -> 16 sums
    // ------------------------------------------------------------------------
    wire [63:0] stage1 [0:15];

    generate
        for (i = 0; i < 16; i = i + 1) begin : GEN_STAGE1
            assign stage1[i] =
                partial_product[2*i] +
                partial_product[2*i + 1];
        end
    endgenerate

    // ------------------------------------------------------------------------
    // Stage 2: 16 sums -> 8 sums
    // ------------------------------------------------------------------------
    wire [63:0] stage2 [0:7];

    generate
        for (i = 0; i < 8; i = i + 1) begin : GEN_STAGE2
            assign stage2[i] =
                stage1[2*i] +
                stage1[2*i + 1];
        end
    endgenerate

    // ------------------------------------------------------------------------
    // Stage 3: 8 sums -> 4 sums
    // ------------------------------------------------------------------------
    wire [63:0] stage3 [0:3];

    generate
        for (i = 0; i < 4; i = i + 1) begin : GEN_STAGE3
            assign stage3[i] =
                stage2[2*i] +
                stage2[2*i + 1];
        end
    endgenerate

    // ------------------------------------------------------------------------
    // Stage 4: 4 sums -> 2 sums
    // ------------------------------------------------------------------------
    wire [63:0] stage4 [0:1];

    assign stage4[0] = stage3[0] + stage3[1];
    assign stage4[1] = stage3[2] + stage3[3];

    // ------------------------------------------------------------------------
    // Stage 5: 2 sums -> final product
    // ------------------------------------------------------------------------
    assign product = stage4[0] + stage4[1];

endmodule

tree_multiplier_32/tree_multiplier_32.srcs/sim_1/new/tb_tree_multiplier_32bit.v
`timescale 1ns / 1ps

module tb_tree_multiplier_32bit;

    reg  [31:0] multiplicand;
    reg  [31:0] multiplier;
    wire [63:0] product;

    reg [63:0] expected_product;

    integer test_count;
    integer pass_count;
    integer fail_count;
    integer i;

    // ------------------------------------------------------------------------
    // DUT instantiation
    // ------------------------------------------------------------------------
    tree_multiplier_32bit DUT (
        .multiplicand(multiplicand),
        .multiplier(multiplier),
        .product(product)
    );

    // ------------------------------------------------------------------------
    // VCD waveform generation
    // ------------------------------------------------------------------------
    initial begin
        $dumpfile("tree_multiplier_32bit.vcd");
        $dumpvars(0, tb_tree_multiplier_32bit);
    end

    // ------------------------------------------------------------------------
    // Task for applying and checking one test vector
    // ------------------------------------------------------------------------
    task check_result;
        input [31:0] a;
        input [31:0] b;
        begin
            multiplicand = a;
            multiplier   = b;

            // Allow combinational logic to settle
            #1;

            expected_product = {32'b0, a} * {32'b0, b};

            test_count = test_count + 1;

            if (product === expected_product) begin
                pass_count = pass_count + 1;
                $display(
                    "PASS: A = %h, B = %h, Product = %h",
                    a, b, product
                );
            end
            else begin
                fail_count = fail_count + 1;
                $display(
                    "FAIL: A = %h, B = %h, Expected = %h, Got = %h",
                    a, b, expected_product, product
                );
            end
        end
    endtask

    // ------------------------------------------------------------------------
    // Test cases
    // ------------------------------------------------------------------------
    initial begin
        test_count = 0;
        pass_count = 0;
        fail_count = 0;

        multiplicand = 32'b0;
        multiplier   = 32'b0;

        #1;

        $display("==============================================");
        $display("32-bit Tree Multiplier Testbench");
        $display("==============================================");

        // ------------------------------------------------------------
        // Basic cases
        // ------------------------------------------------------------
        check_result(32'd0,  32'd0);
        check_result(32'd0,  32'd12345);
        check_result(32'd12345, 32'd0);
        check_result(32'd1,  32'd1);
        check_result(32'd1,  32'd12345);
        check_result(32'd12345, 32'd1);

        // ------------------------------------------------------------
        // Boundary cases
        // ------------------------------------------------------------
        check_result(32'hFFFFFFFF, 32'd0);
        check_result(32'hFFFFFFFF, 32'd1);
        check_result(32'hFFFFFFFF, 32'hFFFFFFFF);

        check_result(32'h80000000, 32'd1);
        check_result(32'h80000000, 32'h80000000);

        check_result(32'h7FFFFFFF, 32'h7FFFFFFF);

        // ------------------------------------------------------------
        // Power-of-two cases
        // ------------------------------------------------------------
        check_result(32'd2,    32'd2);
        check_result(32'd4,    32'd8);
        check_result(32'd16,   32'd16);
        check_result(32'd256,  32'd1024);
        check_result(32'd65536, 32'd65536);

        // ------------------------------------------------------------
        // Mixed-value directed cases
        // ------------------------------------------------------------
        check_result(32'd123, 32'd456);
        check_result(32'd1000, 32'd1000);
        check_result(32'd65535, 32'd65535);
        check_result(32'h12345678, 32'h0000FFFF);
        check_result(32'hAAAAAAAA, 32'h55555555);
        check_result(32'hDEADBEEF, 32'h12345678);

        // ------------------------------------------------------------
        // Random test cases
        // ------------------------------------------------------------
        for (i = 0; i < 100; i = i + 1) begin
            check_result($random, $random);
        end

        // ------------------------------------------------------------
        // Final summary
        // ------------------------------------------------------------
        $display("==============================================");
        $display("Test Summary");
        $display("Total Tests : %0d", test_count);
        $display("Passed      : %0d", pass_count);
        $display("Failed      : %0d", fail_count);
        $display("==============================================");

        if (fail_count == 0) begin
            $display("ALL TESTS PASSED");
        end
        else begin
            $display("TESTS FAILED");
        end

        $finish;
    end

endmodule

tree_multiplier_32/tree_multiplier_32.sim/sim_1/behav/xsim/tree_multiplier_32bit.vcd
$date
   Wed Sep 30 15:41:18 2026
$end

$version
  2026.1
  $dumpfile ("tree_multiplier_32bit.vcd") 
$end

$timescale
  1ps
$end

$scope module tb_tree_multiplier_32bit $end
$var reg 32 ! multiplicand [31:0] $end
$var reg 32 " multiplier [31:0] $end
$var wire 64 # product [63:0] $end
$var reg 64 $ expected_product [63:0] $end
$var integer 32 % test_count [31:0] $end
$var integer 32 & pass_count [31:0] $end
$var integer 32 ' fail_count [31:0] $end
$var integer 32 ( i [31:0] $end
$scope module DUT $end
$var wire 32 ) multiplicand [31:0] $end
$var wire 32 * multiplier [31:0] $end
$var wire 64 # product [63:0] $end
$upscope $end
$scope task check_result $end
$var reg 32 + a [31:0] $end
$var reg 32 , b [31:0] $end
$upscope $end
$upscope $end
$enddefinitions $end

#0
$dumpvars
b0 !
b0 "
b0 #
bx $
b0 %
b0 &
b0 '
bx (
b0 )
b0 *
bx +
bx ,
$end

#1000
b0 +
b0 ,

#2000
b11000000111001 "
b0 $
b1 %
b1 &
b11000000111001 *
b11000000111001 ,

#3000
b11000000111001 !
b0 "
b10 %
b10 &
b11000000111001 )
b0 *
b11000000111001 +
b0 ,

#4000
b1 !
b1 "
b1 #
b11 %
b11 &
b1 )
b1 *
b1 +
b1 ,

#5000
b11000000111001 "
b11000000111001 #
b1 $
b100 %
b100 &
b11000000111001 *
b11000000111001 ,

#6000
b11000000111001 !
b1 "
b11000000111001 $
b101 %
b101 &
b11000000111001 )
b1 *
b11000000111001 +
b1 ,

#7000
b11111111111111111111111111111111 !
b0 "
b0 #
b110 %
b110 &
b11111111111111111111111111111111 )
b0 *
b11111111111111111111111111111111 +
b0 ,

#8000
b1 "
b11111111111111111111111111111111 #
b0 $
b111 %
b111 &
b1 *
b1 ,

#9000
b11111111111111111111111111111111 "
b1111111111111111111111111111111000000000000000000000000000000001 #
b11111111111111111111111111111111 $
b1000 %
b1000 &
b11111111111111111111111111111111 *
b11111111111111111111111111111111 ,

#10000
b10000000000000000000000000000000 !
b1 "
b10000000000000000000000000000000 #
b1111111111111111111111111111111000000000000000000000000000000001 $
b1001 %
b1001 &
b10000000000000000000000000000000 )
b1 *
b10000000000000000000000000000000 +
b1 ,

#11000
b10000000000000000000000000000000 "
b100000000000000000000000000000000000000000000000000000000000000 #
b10000000000000000000000000000000 $
b1010 %
b1010 &
b10000000000000000000000000000000 *
b10000000000000000000000000000000 ,

#12000
b1111111111111111111111111111111 !
b1111111111111111111111111111111 "
b11111111111111111111111111111100000000000000000000000000000001 #
b100000000000000000000000000000000000000000000000000000000000000 $
b1011 %
b1011 &
b1111111111111111111111111111111 )
b1111111111111111111111111111111 *
b1111111111111111111111111111111 +
b1111111111111111111111111111111 ,

#13000
b10 !
b10 "
b100 #
b11111111111111111111111111111100000000000000000000000000000001 $
b1100 %
b1100 &
b10 )
b10 *
b10 +
b10 ,

#14000
b100 !
b1000 "
b100000 #
b100 $
b1101 %
b1101 &
b100 )
b1000 *
b100 +
b1000 ,

#15000
b10000 !
b10000 "
b100000000 #
b100000 $
b1110 %
b1110 &
b10000 )
b10000 *
b10000 +
b10000 ,

#16000
b100000000 !
b10000000000 "
b1000000000000000000 #
b100000000 $
b1111 %
b1111 &
b100000000 )
b10000000000 *
b100000000 +
b10000000000 ,

#17000
b10000000000000000 !
b10000000000000000 "
b100000000000000000000000000000000 #
b1000000000000000000 $
b10000 %
b10000 &
b10000000000000000 )
b10000000000000000 *
b10000000000000000 +
b10000000000000000 ,

#18000
b1111011 !
b111001000 "
b1101101100011000 #
b100000000000000000000000000000000 $
b10001 %
b10001 &
b1111011 )
b111001000 *
b1111011 +
b111001000 ,

#19000
b1111101000 !
b1111101000 "
b11110100001001000000 #
b1101101100011000 $
b10010 %
b10010 &
b1111101000 )
b1111101000 *
b1111101000 +
b1111101000 ,

#20000
b1111111111111111 !
b1111111111111111 "
b11111111111111100000000000000001 #
b11110100001001000000 $
b10011 %
b10011 &
b1111111111111111 )
b1111111111111111 *
b1111111111111111 +
b1111111111111111 ,

#21000
b10010001101000101011001111000 !
b100100011010001000100010000111010100110001000 #
b11111111111111100000000000000001 $
b10100 %
b10100 &
b10010001101000101011001111000 )
b10010001101000101011001111000 +

#22000
b10101010101010101010101010101010 !
b1010101010101010101010101010101 "
b11100011100011100011100011100001110001110001110001110001110010 #
b100100011010001000100010000111010100110001000 $
b10101 %
b10101 &
b10101010101010101010101010101010 )
b1010101010101010101010101010101 *
b10101010101010101010101010101010 +
b1010101010101010101010101010101 ,

#23000
b11011110101011011011111011101111 !
b10010001101000101011001111000 "
b111111010101101111011110111001010110001000011100101000001000 #
b11100011100011100011100011100001110001110001110001110001110010 $
b10110 %
b10110 &
b11011110101011011011111011101111 )
b10010001101000101011001111000 *
b11011110101011011011111011101111 +
b10010001101000101011001111000 ,

#24000
b10010000101010011010100100100 !
b11000000100010010101111010000001 "
b110110011001100110111110000101010110011101101111111100100100 #
b111111010101101111011110111001010110001000011100101000001000 $
b10111 %
b10111 &
b0 (
b10010000101010011010100100100 )
b11000000100010010101111010000001 *
b10010000101010011010100100100 +
b11000000100010010101111010000001 ,

#25000
b10000100100001001101011000001001 !
b10110001111100000101011001100011 "
b101110000011100010000010011110011000000101101011100101101111011 #
b110110011001100110111110000101010110011101101111111100100100 $
b11000 %
b11000 &
b1 (
b10000100100001001101011000001001 )
b10110001111100000101011001100011 *
b10000100100001001101011000001001 +
b10110001111100000101011001100011 ,

#26000
b110101110010111101100001101 !
b1000110110111111001100110001101 "
b111011100100101110100000001001101000001101000101100101001 #
b101110000011100010000010011110011000000101101011100101101111011 $
b11001 %
b11001 &
b10 (
b110101110010111101100001101 )
b1000110110111111001100110001101 *
b110101110010111101100001101 +
b1000110110111111001100110001101 ,

#27000
b10110010110000101000010001100101 !
b10001001001101110101001000010010 "
b101111111010000101110011111001101011110110010001010100100011010 #
b111011100100101110100000001001101000001101000101100101001 $
b11010 %
b11010 &
b11 (
b10110010110000101000010001100101 )
b10001001001101110101001000010010 *
b10110010110000101000010001100101 +
b10001001001101110101001000010010 ,

#28000
b111100111110001100000001 !
b110110101111100110100001101 "
b110100001001110100100000101000000010101010000001101 #
b101111111010000101110011111001101011110110010001010100100011010 $
b11011 %
b11011 &
b100 (
b111100111110001100000001 )
b110110101111100110100001101 *
b111100111110001100000001 +
b110110101111100110100001101 ,

#29000
b111011001000111111000101110110 !
b11110100011011100110100111101 "
b11100001110111110001000000110110001111010100000011100011110 #
b110100001001110100100000101000000010101010000001101 $
b11100 %
b11100 &
b101 (
b111011001000111111000101110110 )
b11110100011011100110100111101 *
b111011001000111111000101110110 +
b11110100011011100110100111101 ,

#30000
b1110110110101000101011111101101 !
b1000110001011011111011110001100 "
b10000010010011011001100100011000011111100111101100000010011100 #
b11100001110111110001000000110110001111010100000011100011110 $
b11101 %
b11101 &
b110 (
b1110110110101000101011111101101 )
b1000110001011011111011110001100 *
b1110110110101000101011111101101 +
b1000110001011011111011110001100 ,

#31000
b1111100111111011110100111111001 !
b11100011001101110010010011000110 "
b110111011110000000100101111100101110000110010001111101010010110 #
b10000010010011011001100100011000011111100111101100000010011100 $
b11110 %
b11110 &
b111 (
b1111100111111011110100111111001 )
b11100011001101110010010011000110 *
b1111100111111011110100111111001 +
b11100011001101110010010011000110 ,

#32000
b11100010111101111000010011000101 !
b11010101000100111101001010101010 "
b1011110011101001100001001001110010000110111001101100010011010010 #
b110111011110000000100101111100101110000110010001111101010010110 $
b11111 %
b11111 &
b1000 (
b11100010111101111000010011000101 )
b11010101000100111101001010101010 *
b11100010111101111000010011000101 +
b11010101000100111101001010101010 ,

#33000
b1110010101011111111011111100101 !
b10111011110100100111001001110111 "
b101010000100100110100011011010101001101000010100011010101110011 #
b1011110011101001100001001001110010000110111001101100010011010010 $
b100000 %
b100000 &
b1001 (
b1110010101011111111011111100101 )
b10111011110100100111001001110111 *
b1110010101011111111011111100101 +
b10111011110100100111001001110111 ,

#34000
b10001001001100101101011000010010 !
b1000111111011001101101110001111 "
b10011010001100000010011110011101110111000111101111101000001110 #
b101010000100100110100011011010101001101000010100011010101110011 $
b100001 %
b100001 &
b1010 (
b10001001001100101101011000010010 )
b1000111111011001101101110001111 *
b10001001001100101101011000010010 +
b1000111111011001101101110001111 ,

#35000
b1111001001100000110100111110010 !
b11100111011101101001011011001110 "
b110110110010010110100110100111000010110100101010000110010111100 #
b10011010001100000010011110011101110111000111101111101000001110 $
b100010 %
b100010 &
b1011 (
b1111001001100000110100111110010 )
b11100111011101101001011011001110 *
b1111001001100000110100111110010 +
b11100111011101101001011011001110 ,

#36000
b11110100000000000111101011101000 !
b11100010110010100100111011000101 "
b1101100000101001001111111111010110110100111000010100010010001000 #
b110110110010010110100110100111000010110100101010000110010111100 $
b100011 %
b100011 &
b1100 (
b11110100000000000111101011101000 )
b11100010110010100100111011000101 *
b11110100000000000111101011101000 +
b11100010110010100100111011000101 ,

#37000
b101110010110000100100101011100 !
b11011110100011100010100010111101 "
b10100001001010010010111111011001111011101011001000100011101100 #
b1101100000101001001111111111010110110100111000010100010010001000 $
b100100 %
b100100 &
b1101 (
b101110010110000100100101011100 )
b11011110100011100010100010111101 *
b101110010110000100100101011100 +
b11011110100011100010100010111101 ,

#38000
b10010110101010110101100000101101 !
b10110010101001110010011001100101 "
b110100100100101100000111010111010110000000010110111011111000001 #
b10100001001010010010111111011001111011101011001000100011101100 $
b100101 %
b100101 &
b1110 (
b10010110101010110101100000101101 )
b10110010101001110010011001100101 *
b10010110101010110101100000101101 +
b10110010101001110010011001100101 ,

#39000
b10110001111011110110001001100011 !
b101011100111000011100001010 "
b1111001001111110010101000101010001101101010000110011011110 #
b110100100100101100000111010111010110000000010110111011111000001 $
b100110 %
b100110 &
b1111 (
b10110001111011110110001001100011 )
b101011100111000011100001010 *
b10110001111011110110001001100011 +
b101011100111000011100001010 ,

#40000
b11000000001110110010001010000000 !
b10000011001000010000100100000 "
b110001001110111000100010000100100000110101101101000000000000 #
b1111001001111110010101000101010001101101010000110011011110 $
b100111 %
b100111 &
b10000 (
b11000000001110110010001010000000 )
b10000011001000010000100100000 *
b11000000001110110010001010000000 +
b10000011001000010000100100000 ,

#41000
b1010101011110000100010110101010 !
b11001110110011001100110010011101 "
b100010100001011001010000011011010010001101111100011000101000010 #
b110001001110111000100010000100100000110101101101000000000000 $
b101000 %
b101000 &
b10001 (
b1010101011110000100010110101010 )
b11001110110011001100110010011101 *
b1010101011110000100010110101010 +
b11001110110011001100110010011101 ,

#42000
b11001011001000000011111010010110 !
b10001001100000111011100000010011 "
b110110100011100110001010000110010001101001000100111010100100010 #
b100010100001011001010000011011010010001101111100011000101000010 $
b101001 %
b101001 &
b10010 (
b11001011001000000011111010010110 )
b10001001100000111011100000010011 *
b11001011001000000011111010010110 +
b10001001100000111011100000010011 ,

#43000
b10000110101111000011100000001101 !
b10101001101001111101011001010011 "
b101100101001010100101101001011000101011010111000000101000110111 #
b110110100011100110001010000110010001101001000100111010100100010 $
b101010 %
b101010 &
b10011 (
b10000110101111000011100000001101 )
b10101001101001111101011001010011 *
b10000110101111000011100000001101 +
b10101001101001111101011001010011 ,

#44000
b110101100111111101110101101011 !
b11101010101001100010101011010101 "
b11000100100110111011110000011000111001101110001100100000000111 #
b101100101001010100101101001011000101011010111000000101000110111 $
b101011 %
b101011 &
b10100 (
b110101100111111101110101101011 )
b11101010101001100010101011010101 *
b110101100111111101110101101011 +
b11101010101001100010101011010101 ,

#45000
b10000001000101110100101000000010 !
b11010111010101100011111010101110 "
b110110010010110000011001001010111101100011011001100100101011100 #
b11000100100110111011110000011000111001101110001100100000000111 $
b101100 %
b101100 &
b10101 (
b10000001000101110100101000000010 )
b11010111010101100011111010101110 *
b10000001000101110100101000000010 +
b11010111010101100011111010101110 ,

#46000
b1110111111111110100100011101 !
b11100111110001010111001011001111 "
b110110010100011111010000000110100101000011010110100001110011 #
b110110010010110000011001001010111101100011011001100100101011100 $
b101101 %
b101101 &
b10110 (
b1110111111111110100100011101 )
b11100111110001010111001011001111 *
b1110111111111110100100011101 +
b11100111110001010111001011001111 ,

#47000
b10001100001000100100100100011 !
b101000010010110010100001010 "
b1011000001110011111111000100001010000001010101001011110 #
b110110010100011111010000000110100101000011010110100001110011 $
b101110 %
b101110 &
b10111 (
b10001100001000100100100100011 )
b101000010010110010100001010 *
b10001100001000100100100100011 +
b101000010010110010100001010 ,

#48000
b11100101011100110000101011001010 !
b10011110001100010100110000111100 "
b1000110111001001001100000000000110101010110101000111111101011000 #
b1011000001110011111111000100001010000001010101001011110 $
b101111 %
b101111 &
b11000 (
b11100101011100110000101011001010 )
b10011110001100010100110000111100 *
b11100101011100110000101011001010 +
b10011110001100010100110000111100 ,

#49000
b1111001011010001011110111110010 !
b1000101001011100110000110001010 "
b10000011001111001110100100011001111101111010110001011001110100 #
b1000110111001001001100000000000110101010110101000111111101011000 $
b110000 %
b110000 &
b11001 (
b1111001011010001011110111110010 )
b1000101001011100110000110001010 *
b1111001011010001011110111110010 +
b1000101001011100110000110001010 ,

#50000
b100000110001001011001101000001 !
b11101100010010110011010011011000 "
b1111000111110111101011010010000001010011010110111001011011000 #
b10000011001111001110100100011001111101111010110001011001110100 $
b110001 %
b110001 &
b11010 (
b100000110001001011001101000001 )
b11101100010010110011010011011000 *
b100000110001001011001101000001 +
b11101100010010110011010011011000 ,

#51000
b111100001000001111001101111000 !
b11000100100010100001001010001001 "
b10111000101001101010001000010110011101011100001011101100111000 #
b1111000111110111101011010010000001010011010110111001011011000 $
b110010 %
b110010 &
b11011 (
b111100001000001111001101111000 )
b11000100100010100001001010001001 *
b111100001000001111001101111000 +
b11000100100010100001001010001001 ,

#52000
b1110101110001010000110111101011 !
b1011011000000100110010110110110 "
b10100111011110001001100100011100011101011010111001110000010010 #
b10111000101001101010001000010110011101011100001011101100111000 $
b110011 %
b110011 &
b11100 (
b1110101110001010000110111101011 )
b1011011000000100110010110110110 *
b1110101110001010000110111101011 +
b1011011000000100110010110110110 ,

#53000
b1100011010010111111100111000110 !
b1010111000101010001001110101110 "
b10000111000110111111101011111111101000011010110111011010010100 #
b10100111011110001001100100011100011101011010111001110000010010 $
b110100 %
b110100 &
b11101 (
b1100011010010111111100111000110 )
b1010111000101010001001110101110 *
b1100011010010111111100111000110 +
b1010111000101010001001110101110 ,

#54000
b11011110011101010000001010111100 !
b10101000011111101110100101010 "
b1001001001101011000100100010000010111100100101011111011011000 #
b10000111000110111111101011111111101000011010110111011010010100 $
b110101 %
b110101 &
b11110 (
b11011110011101010000001010111100 )
b10101000011111101110100101010 *
b11011110011101010000001010111100 +
b10101000011111101110100101010 ,

#55000
b10000101110101111001101000001011 !
b10111000100101111011111001110001 "
b110000010000010010011000111010011011100111111000010100011011011 #
b1001001001101011000100100010000010111100100101011111011011000 $
b110110 %
b110110 &
b11111 (
b10000101110101111001101000001011 )
b10111000100101111011111001110001 *
b10000101110101111001101000001011 +
b10111000100101111011111001110001 ,

#56000
b1000010111100100100000110000101 !
b100111111100100101010101001111 "
b101001110010010001110100110001001011001111010110000100001011 #
b110000010000010010011000111010011011100111111000010100011011011 $
b110111 %
b110111 &
b100000 (
b1000010111100100100000110000101 )
b100111111100100101010101001111 *
b1000010111100100100000110000101 +
b100111111100100101010101001111 ,

#57000
b10011101110011000110000000111011 !
b11101000001100011001100111010 "
b1000111100011111110010100010001100111110110111000111001011110 #
b101001110010010001110100110001001011001111010110000100001011 $
b111000 %
b111000 &
b100001 (
b10011101110011000110000000111011 )
b11101000001100011001100111010 *
b10011101110011000110000000111011 +
b11101000001100011001100111010 ,

#58000
b10111111001000110011001001111110 !
b1010101010100100101100010101 "
b11111110110100001010110011101110001010110100000111001010110 #
b1000111100011111110010100010001100111110110111000111001011110 $
b111001 %
b111001 &
b100010 (
b10111111001000110011001001111110 )
b1010101010100100101100010101 *
b10111111001000110011001001111110 +
b1010101010100100101100010101 ,

#59000
b1111000110110011001101111110001 !
b1101100100111000100101111011001 "
b11001101000101100101100011001011100100000000001100101001001001 #
b11111110110100001010110011101110001010110100000111001010110 $
b111010 %
b111010 &
b100011 (
b1111000110110011001101111110001 )
b1101100100111000100101111011001 *
b1111000110110011001101111110001 +
b1101100100111000100101111011001 ,

#60000
b110001001000110000011101100010 !
b100110001101011111101101001100 "
b11101010101100011111001010100000001111011010100011100011000 #
b11001101000101100101100011001011100100000000001100101001001001 $
b111011 %
b111011 &
b100100 (
b110001001000110000011101100010 )
b100110001101011111101101001100 *
b110001001000110000011101100010 +
b100110001101011111101101001100 ,

#61000
b1001111101000010101010110011111 !
b1000111101110011010000110001111 "
b1011001001111011111001001011011101010110111101101001011010001 #
b11101010101100011111001010100000001111011010100011100011000 $
b111100 %
b111100 &
b100101 (
b1001111101000010101010110011111 )
b1000111101110011010000110001111 *
b1001111101000010101010110011111 +
b1000111101110011010000110001111 ,

#62000
b1111100011011011010100111111000 !
b11011011110011010110000010110111 "
b110101011010101101000110011101001010101101110011000000001001000 #
b1011001001111011111001001011011101010110111101101001011010001 $
b111101 %
b111101 &
b100110 (
b1111100011011011010100111111000 )
b11011011110011010110000010110111 *
b1111100011011011010100111111000 +
b11011011110011010110000010110111 ,

#63000
b11001111110001000101011010011111 !
b10101110011111011001010001011100 "
b1000110110011101010111100010011010001010010001100000110100100100 #
b110101011010101101000110011101001010101101110011000000001001000 $
b111110 %
b111110 &
b100111 (
b11001111110001000101011010011111 )
b10101110011111011001010001011100 *
b11001111110001000101011010011111 +
b10101110011111011001010001011100 ,

#64000
b10101101110010111100000001011011 !
b1000100110111100011011110001001 "
b10111011000000111110110111110011000011010001110111110110110011 #
b1000110110011101010111100010011010001010010001100000110100100100 $
b111111 %
b111111 &
b101000 (
b10101101110010111100000001011011 )
b1000100110111100011011110001001 *
b10101101110010111100000001011011 +
b1000100110111100011011110001001 ,

#65000
b10100100101011100011001001001001 !
b11101000001000110011111011010000 "
b1001010101010100100010011100101100000101101100011000100101010000 #
b10111011000000111110110111110011000011010001110111110110110011 $
b1000000 %
b1000000 &
b101001 (
b10100100101011100011001001001001 )
b11101000001000110011111011010000 *
b10100100101011100011001001001001 +
b11101000001000110011111011010000 ,

#66000
b11101011111111101100000011010111 !
b10101000110001111111110001010001 "
b1001101110010111100010100010111001110000100011111010100000000111 #
b1001010101010100100010011100101100000101101100011000100101010000 $
b1000001 %
b1000001 &
b101010 (
b11101011111111101100000011010111 )
b10101000110001111111110001010001 *
b11101011111111101100000011010111 +
b10101000110001111111110001010001 ,

#67000
b1001011001000010010111110010110 !
b110000111010111111100001100 "
b111001011011011110010100011100100001001111010010100001000 #
b1001101110010111100010100010111001110000100011111010100000000111 $
b1000010 %
b1000010 &
b101011 (
b1001011001000010010111110010110 )
b110000111010111111100001100 *
b1001011001000010010111110010110 +
b110000111010111111100001100 ,

#68000
b11100001001011001100111011000010 !
b1100100010101111110110111001000 "
b101100001000010110110000010010001110010010110010010000110010000 #
b111001011011011110010100011100100001001111010010100001000 $
b1000011 %
b1000011 &
b101100 (
b11100001001011001100111011000010 )
b1100100010101111110110111001000 *
b11100001001011001100111011000010 +
b1100100010101111110110111001000 ,

#69000
b10111011100000100101101001110111 !
b11110111100101110110100111101 "
b1011010101011001101011001011111010010010011011011100101011011 #
b101100001000010110110000010010001110010010110010010000110010000 $
b1000100 %
b1000100 &
b101101 (
b10111011100000100101101001110111 )
b11110111100101110110100111101 *
b10111011100000100101101001110111 +
b11110111100101110110100111101 ,

#70000
b1001000011001101101100010010 !
b10111111000001010000000001111110 "
b11011000000110001001011011100101001101011011101001011011100 #
b1011010101011001101011001011111010010010011011011100101011011 $
b1000101 %
b1000101 &
b101110 (
b1001000011001101101100010010 )
b10111111000001010000000001111110 *
b1001000011001101101100010010 +
b10111111000001010000000001111110 ,

#71000
b110110111001011000000101101101 !
b11100110110011110011100111001 "
b11000101111110101000100011111110010010010000010110001000101 #
b11011000000110001001011011100101001101011011101001011011100 $
b1000110 %
b1000110 &
b101111 (
b110110111001011000000101101101 )
b11100110110011110011100111001 *
b110110111001011000000101101101 +
b11100110110011110011100111001 ,

#72000
b1111110100101000111100011111 !
b11101001111010111111011011010011 "
b111001110101001110011100110111111000100010001100000010001101 #
b11000101111110101000100011111110010010010000010110001000101 $
b1000111 %
b1000111 &
b110000 (
b1111110100101000111100011111 )
b11101001111010111111011011010011 *
b1111110100101000111100011111 +
b11101001111010111111011011010011 ,

#73000
b1000010110110010010111110000101 !
b10111100000101001000100001111000 "
b11000100011100110110111000000000011001011100001110111001011000 #
b111001110101001110011100110111111000100010001100000010001101 $
b1001000 %
b1001000 &
b110001 (
b1000010110110010010111110000101 )
b10111100000101001000100001111000 *
b1000010110110010010111110000101 +
b10111100000101001000100001111000 ,

#74000
b101101110110100101100101011011 !
b100100100010110100101101001001 "
b11010001011101001111001101101011011110110100010001111110011 #
b11000100011100110110111000000000011001011100001110111001011000 $
b1001001 %
b1001001 &
b110010 (
b101101110110100101100101011011 )
b100100100010110100101101001001 *
b101101110110100101100101011011 +
b100100100010110100101101001001 ,

#75000
b10011111111100101010111000111111 !
b10101000011001010111100101010 "
b110100100110110101010001110001111000111000011010011101010110 #
b11010001011101001111001101101011011110110100010001111110011 $
b1001010 %
b1001010 &
b110011 (
b10011111111100101010111000111111 )
b10101000011001010111100101010 *
b10011111111100101010111000111111 +
b10101000011001010111100101010 ,

#76000
b101100000101010110001101011000 !
b11000011001111110011100010000110 "
b10000110011111001011011010101100111011100101010100000000010000 #
b110100100110110101010001110001111000111000011010011101010110 $
b1001011 %
b1001011 &
b110100 (
b101100000101010110001101011000 )
b11000011001111110011100010000110 *
b101100000101010110001101011000 +
b11000011001111110011100010000110 ,

#77000
b11000111000110100000110010001110 !
b11001110001011111111001010011100 "
b1010000001011100010000001001001010000101110011111110001010001000 #
b10000110011111001011011010101100111011100101010100000000010000 $
b1001100 %
b1001100 &
b110101 (
b11000111000110100000110010001110 )
b11001110001011111111001010011100 *
b11000111000110100000110010001110 +
b11001110001011111111001010011100 ,

#78000
b1111101001101011001100111111010 !
b10010011011111011011110000100110 "
b100100000100011010001101001110010110000000110100111001100011100 #
b1010000001011100010000001001001010000101110011111110001010001000 $
b1001101 %
b1001101 &
b110110 (
b1111101001101011001100111111010 )
b10010011011111011011110000100110 *
b1111101001101011001100111111010 +
b10010011011111011011110000100110 ,

#79000
b111001100101100001011101110011 !
b11010001100010111011010010100011 "
b10111100100010111101100100010111010001011111101100101000111001 #
b100100000100011010001101001110010110000000110100111001100011100 $
b1001110 %
b1001110 &
b110111 (
b111001100101100001011101110011 )
b11010001100010111011010010100011 *
b111001100101100001011101110011 +
b11010001100010111011010010100011 ,

#80000
b10010111100110011010100000101111 !
b11011001110100101001001010110011 "
b1000000011111101111100100111101101101111111010010110011011011101 #
b10111100100010111101100100010111010001011111101100101000111001 $
b1001111 %
b1001111 &
b111000 (
b10010111100110011010100000101111 )
b11011001110100101001001010110011 *
b10010111100110011010100000101111 +
b11011001110100101001001010110011 ,

#81000
b10101111110110000101011001011111 !
b100010001010010000110101000100 "
b1011101110110111011100011101100100101000100001100010000111100 #
b1000000011111101111100100111101101101111111010010110011011011101 $
b1010000 %
b1010000 &
b111001 (
b10101111110110000101011001011111 )
b100010001010010000110101000100 *
b10101111110110000101011001011111 +
b100010001010010000110101000100 ,

#82000
b1111011111110001111110111110111 !
b11100101100110110011011011001011 "
b110111100110000111001010111100010001011100100000111110011011101 #
b1011101110110111011100011101100100101000100001100010000111100 $
b1010001 %
b1010001 &
b111010 (
b1111011111110001111110111110111 )
b11100101100110110011011011001011 *
b1111011111110001111110111110111 +
b11100101100110110011011011001011 ,

#83000
b11110011000010010001101011100110 !
b101101001010001101101101011010 "
b10101011011111011000110110010011011101001001100011011011011100 #
b110111100110000111001010111100010001011100100000111110011011101 $
b1010010 %
b1010010 &
b111011 (
b11110011000010010001101011100110 )
b101101001010001101101101011010 *
b11110011000010010001101011100110 +
b101101001010001101101101011010 ,

