CSA_16/CSA_16.srcs/sources_1/new/carry_select_adder_16bit.v
module carry_select_adder_16bit (
    input  [15:0] a,
    input  [15:0] b,
    input         cin,
    output [15:0] sum,
    output        cout
);

    wire [8:0] lower_result;

    wire [8:0] upper_sum_cin0;
    wire [8:0] upper_sum_cin1;

    wire [7:0] upper_sum;

    // Lower 8-bit addition
    assign lower_result = {1'b0, a[7:0]}
                        + {1'b0, b[7:0]}
                        + cin;

    // Upper 8-bit addition assuming carry-in = 0
    assign upper_sum_cin0 = {1'b0, a[15:8]}
                          + {1'b0, b[15:8]};

    // Upper 8-bit addition assuming carry-in = 1
    assign upper_sum_cin1 = {1'b0, a[15:8]}
                          + {1'b0, b[15:8]}
                          + 1'b1;

    // Select the correct upper result
    assign upper_sum = lower_result[8]
                     ? upper_sum_cin1[7:0]
                     : upper_sum_cin0[7:0];

    // Combine lower and upper sums
    assign sum = {upper_sum, lower_result[7:0]};

    // Select the corresponding final carry-out
    assign cout = lower_result[8]
                ? upper_sum_cin1[8]
                : upper_sum_cin0[8];

endmodule

CSA_16/CSA_16.srcs/sim_1/new/tb_carry_select_adder_16bit.v
`timescale 1ns / 1ps

module tb_carry_select_adder_16bit;

    reg  [15:0] a;
    reg  [15:0] b;
    reg         cin;

    wire [15:0] sum;
    wire        cout;

    reg  [16:0] expected;

    integer i;
    integer pass_count;
    integer fail_count;

    // Instantiate the DUT
    carry_select_adder_16bit uut (
        .a(a),
        .b(b),
        .cin(cin),
        .sum(sum),
        .cout(cout)
    );

    // Task to apply inputs and check the result
    task check_result;
        input [15:0] test_a;
        input [15:0] test_b;
        input        test_cin;
        begin
            a = test_a;
            b = test_b;
            cin = test_cin;

            // Allow combinational logic to settle
            #10;

            // Calculate expected result
            expected = {1'b0, test_a}
                     + {1'b0, test_b}
                     + test_cin;

            // Compare DUT output with expected result
            if ({cout, sum} === expected) begin
                pass_count = pass_count + 1;
            end
            else begin
                fail_count = fail_count + 1;

                $display("FAIL: a=%h, b=%h, cin=%b", a, b, cin);
                $display("Expected: %h, Actual: %h",
                         expected, {cout, sum});
            end
        end
    endtask

    initial begin
        // Initialize signals and counters
        a = 16'b0;
        b = 16'b0;
        cin = 1'b0;

        pass_count = 0;
        fail_count = 0;

        // Generate VCD waveform
        $dumpfile("carry_select_adder.vcd");
        $dumpvars(0, tb_carry_select_adder_16bit);

        // Directed test cases

        // Zero inputs
        check_result(16'h0000, 16'h0000, 1'b0);

        // Carry-in only
        check_result(16'h0000, 16'h0000, 1'b1);

        // Maximum values
        check_result(16'hFFFF, 16'hFFFF, 1'b0);
        check_result(16'hFFFF, 16'hFFFF, 1'b1);

        // Carry propagation across lower and upper sections
        check_result(16'h00FF, 16'h0001, 1'b0);
        check_result(16'h0FFF, 16'h0001, 1'b0);
        check_result(16'hFFFF, 16'h0001, 1'b0);

        // Carry-select upper section cases
        check_result(16'h00FF, 16'hFF00, 1'b0);
        check_result(16'h0100, 16'h0100, 1'b0);
        check_result(16'hFF00, 16'h0100, 1'b0);
        check_result(16'hFFFF, 16'h0000, 1'b1);

        // Alternating bit patterns
        check_result(16'hAAAA, 16'h5555, 1'b0);
        check_result(16'h5555, 16'hAAAA, 1'b1);

        // Randomized test cases
        for (i = 0; i < 1000; i = i + 1) begin
            check_result($random, $random, $random);
        end

        // Final test summary
        $display("--------------------------------");
        $display("Testbench Summary");
        $display("Total tests : %0d", pass_count + fail_count);
        $display("Passed      : %0d", pass_count);
        $display("Failed      : %0d", fail_count);
        $display("--------------------------------");

        if (fail_count == 0)
            $display("TEST PASSED");
        else
            $display("TEST FAILED");

        $finish;
    end

endmodule

CSA_16/CSA_16.sim/sim_1/behav/xsim/carry_select_adder.vcd
$date
   Tue Sep 29 15:45:35 2026
$end

$version
  2026.1
  $dumpfile ("carry_select_adder.vcd") 
$end

$timescale
  1ps
$end

$scope module tb_carry_select_adder_16bit $end
$var reg 16 ! a [15:0] $end
$var reg 16 " b [15:0] $end
$var reg 1 # cin $end
$var wire 16 $ sum [15:0] $end
$var wire 1 % cout $end
$var reg 17 & expected [16:0] $end
$var integer 32 ' i [31:0] $end
$var integer 32 ( pass_count [31:0] $end
$var integer 32 ) fail_count [31:0] $end
$scope module uut $end
$var wire 16 * a [15:0] $end
$var wire 16 + b [15:0] $end
$var wire 1 , cin $end
$var wire 16 $ sum [15:0] $end
$var wire 1 % cout $end
$var wire 9 - lower_result [8:0] $end
$var wire 9 . upper_sum_cin0 [8:0] $end
$var wire 9 / upper_sum_cin1 [8:0] $end
$var wire 8 0 upper_sum [7:0] $end
$upscope $end
$scope task check_result $end
$var reg 16 1 test_a [15:0] $end
$var reg 16 2 test_b [15:0] $end
$var reg 1 3 test_cin $end
$upscope $end
$upscope $end
$enddefinitions $end

#0
$dumpvars
b0 !
b0 "
0#
b0 $
0%
bx &
bx '
b0 (
b0 )
b0 *
b0 +
0,
b0 -
b0 .
b1 /
b0 0
b0 1
b0 2
03
$end

#10000
1#
b1 $
b0 &
b1 (
1,
b1 -
13

#20000
b1111111111111111 !
b1111111111111111 "
0#
b1111111111111110 $
1%
b1 &
b10 (
b1111111111111111 *
b1111111111111111 +
0,
b111111110 -
b111111110 .
b111111111 /
b11111111 0
b1111111111111111 1
b1111111111111111 2
03

#30000
1#
b1111111111111111 $
b11111111111111110 &
b11 (
1,
b111111111 -
13

#40000
b11111111 !
b1 "
0#
b100000000 $
0%
b11111111111111111 &
b100 (
b11111111 *
b1 +
0,
b100000000 -
b0 .
b1 /
b1 0
b11111111 1
b1 2
03

#50000
b111111111111 !
b1000000000000 $
b100000000 &
b101 (
b111111111111 *
b1111 .
b10000 /
b10000 0
b111111111111 1

#60000
b1111111111111111 !
b0 $
1%
b1000000000000 &
b110 (
b1111111111111111 *
b11111111 .
b100000000 /
b0 0
b1111111111111111 1

#70000
b11111111 !
b1111111100000000 "
b1111111111111111 $
0%
b10000000000000000 &
b111 (
b11111111 *
b1111111100000000 +
b11111111 -
b11111111 0
b11111111 1
b1111111100000000 2

#80000
b100000000 !
b100000000 "
b1000000000 $
b1111111111111111 &
b1000 (
b100000000 *
b100000000 +
b0 -
b10 .
b11 /
b10 0
b100000000 1
b100000000 2

#90000
b1111111100000000 !
b0 $
1%
b1000000000 &
b1001 (
b1111111100000000 *
b100000000 .
b100000001 /
b0 0
b1111111100000000 1

#100000
b1111111111111111 !
b0 "
1#
b10000000000000000 &
b1010 (
b1111111111111111 *
b0 +
1,
b100000000 -
b11111111 .
b100000000 /
b1111111111111111 1
b0 2
13

#110000
b1010101010101010 !
b101010101010101 "
0#
b1111111111111111 $
0%
b1011 (
b1010101010101010 *
b101010101010101 +
0,
b11111111 -
b11111111 0
b1010101010101010 1
b101010101010101 2
03

#120000
b101010101010101 !
b1010101010101010 "
1#
b0 $
1%
b1111111111111111 &
b1100 (
b101010101010101 *
b1010101010101010 +
1,
b100000000 -
b0 0
b101010101010101 1
b1010101010101010 2
13

#130000
b11010100100100 !
b101111010000001 "
b1001001110100110 $
0%
b10000000000000000 &
b0 '
b1101 (
b11010100100100 *
b101111010000001 +
b10100110 -
b10010011 .
b10010100 /
b10010011 0
b11010100100100 1
b101111010000001 2

#140000
b101011001100011 !
b111101100001101 "
b1101000101110001 $
b1001001110100110 &
b1 '
b1110 (
b101011001100011 *
b111101100001101 +
b1110001 -
b11010001 .
b11010010 /
b11010001 0
b101011001100011 1
b111101100001101 2

#150000
b1000010001100101 !
b101001000010010 "
b1101011001111000 $
b1101000101110001 &
b10 '
b1111 (
b1000010001100101 *
b101001000010010 +
b1111000 -
b11010110 .
b11010111 /
b11010110 0
b1000010001100101 1
b101001000010010 2

#160000
b1100110100001101 !
b1111000101110110 "
b1011111010000100 $
1%
b1101011001111000 &
b11 '
b10000 (
b1100110100001101 *
b1111000101110110 +
b10000100 -
b110111110 .
b110111111 /
b10111110 0
b1100110100001101 1
b1111000101110110 2

#170000
b101011111101101 !
b1111011110001100 "
b100111101111010 $
b11011111010000100 &
b100 '
b10001 (
b101011111101101 *
b1111011110001100 +
b101111010 -
b101001110 .
b101001111 /
b1001111 0
b101011111101101 1
b1111011110001100 2

#180000
b10010011000110 !
b1000010011000101 "
0#
b1010100110001011 $
0%
b10100111101111010 &
b101 '
b10010 (
b10010011000110 *
b1000010011000101 +
0,
b110001011 -
b10101000 .
b10101001 /
b10101001 0
b10010011000110 1
b1000010011000101 2
03

#190000
b1111011111100101 !
b111001001110111 "
b110101001011100 $
1%
b1010100110001011 &
b110 '
b10011 (
b1111011111100101 *
b111001001110111 +
b101011100 -
b101101001 .
b101101010 /
b1101010 0
b1111011111100101 1
b111001001110111 2

#200000
b1101101110001111 !
b110100111110010 "
b100010110000001 $
b10110101001011100 &
b111 '
b10100 (
b1101101110001111 *
b110100111110010 +
b110000001 -
b101000100 .
b101000101 /
b1000101 0
b1101101110001111 1
b110100111110010 2

#210000
b111101011101000 !
b100111011000101 "
b1100100110101101 $
0%
b10100010110000001 &
b1000 '
b10101 (
b111101011101000 *
b100111011000101 +
b110101101 -
b11001000 .
b11001001 /
b11001001 0
b111101011101000 1
b100111011000101 2

#220000
b10100010111101 !
b101100000101101 "
1#
b1000000011101011 $
b1100100110101101 &
b1001 '
b10110 (
b10100010111101 *
b101100000101101 +
1,
b11101011 -
b10000000 .
b10000001 /
b10000000 0
b10100010111101 1
b101100000101101 2
13

#230000
b110001001100011 !
b1000011100001010 "
0#
b1110100101101101 $
b1000000011101011 &
b1010 '
b10111 (
b110001001100011 *
b1000011100001010 +
0,
b1101101 -
b11101001 .
b11101010 /
b11101001 0
b110001001100011 1
b1000011100001010 2
03

#240000
b10000100100000 !
b100010110101010 "
1#
b110011011001011 $
b1110100101101101 &
b1011 '
b11000 (
b10000100100000 *
b100010110101010 +
1,
b11001011 -
b1100110 .
b1100111 /
b1100110 0
b10000100100000 1
b100010110101010 2
13

#250000
b11111010010110 !
b1011100000010011 "
b1111011010101010 $
b110011011001011 &
b1100 '
b11001 (
b11111010010110 *
b1011100000010011 +
b10101010 -
b11110110 .
b11110111 /
b11110110 0
b11111010010110 1
b1011100000010011 2

#260000
b1101011001010011 !
b1101110101101011 "
b1011001110111111 $
1%
b1111011010101010 &
b1101 '
b11010 (
b1101011001010011 *
b1101110101101011 +
b10111111 -
b110110011 .
b110110100 /
b10110011 0
b1101011001010011 1
b1101110101101011 2

#270000
b100101000000010 !
b11111010101110 "
b1000100010110001 $
0%
b11011001110111111 &
b1110 '
b11011 (
b100101000000010 *
b11111010101110 +
b10110001 -
b10001000 .
b10001001 /
b10001000 0
b100101000000010 1
b11111010101110 2

#280000
b111001011001111 !
b100100100100011 "
0#
b1011101111110010 $
b1000100010110001 &
b1111 '
b11100 (
b111001011001111 *
b100100100100011 +
0,
b11110010 -
b10111011 .
b10111100 /
b10111011 0
b111001011001111 1
b100100100100011 2
03

#290000
b101011001010 !
b100110000111100 "
b101011100000110 $
b1011101111110010 &
b10000 '
b11101 (
b101011001010 *
b100110000111100 +
b100000110 -
b1010110 .
b1010111 /
b1010111 0
b101011001010 1
b100110000111100 2

#300000
b110000110001010 !
b1011001101000001 "
b1010011001011 $
1%
b101011100000110 &
b10001 '
b11110 (
b110000110001010 *
b1011001101000001 +
b11001011 -
b100010100 .
b100010101 /
b10100 0
b110000110001010 1
b1011001101000001 2

#310000
b1111001101111000 !
b1001010001001 "
1#
b11000000010 $
b10001010011001011 &
b10010 '
b11111 (
b1111001101111000 *
b1001010001001 +
1,
b100000010 -
b100000101 .
b100000110 /
b110 0
b1111001101111000 1
b1001010001001 2
13

#320000
b110010110110110 !
b1111100111000110 "
0#
b101111101111100 $
b10000011000000010 &
b10011 '
b100000 (
b110010110110110 *
b1111100111000110 +
0,
b101111100 -
b101011110 .
b101011111 /
b1011111 0
b110010110110110 1
b1111100111000110 2
03

#330000
b1010111100 !
b1101110100101010 "
1#
b1101111111100111 $
0%
b10101111101111100 &
b10100 '
b100001 (
b1010111100 *
b1101110100101010 +
1,
b11100111 -
b11011111 .
b11100000 /
b11011111 0
b1010111100 1
b1101110100101010 2
13

#340000
b1011111001110001 !
b100000110000101 "
b1111111111110111 $
b1101111111100111 &
b10101 '
b100010 (
b1011111001110001 *
b100000110000101 +
b11110111 -
b11111111 .
b100000000 /
b11111111 0
b1011111001110001 1
b100000110000101 2

#350000
b110000000111011 !
b11001100111010 "
0#
b1001001101110101 $
b1111111111110111 &
b10110 '
b100011 (
b110000000111011 *
b11001100111010 +
0,
b1110101 -
b10010011 .
b10010100 /
b10010011 0
b110000000111011 1
b11001100111010 2
03

#360000
b100101100010101 !
b1001101111110001 "
1#
b1110011100000111 $
b1001001101110101 &
b10111 '
b100100 (
b100101100010101 *
b1001101111110001 +
1,
b100000111 -
b11100110 .
b11100111 /
b11100111 0
b100101100010101 1
b1001101111110001 2
13

#370000
b11101100010 !
b1111101101001100 "
b1010101111 $
1%
b1110011100000111 &
b11000 '
b100101 (
b11101100010 *
b1111101101001100 +
b10101111 -
b100000010 .
b100000011 /
b10 0
b11101100010 1
b1111101101001100 2

#380000
b1010000110001111 !
b1010100111111000 "
b100101110001000 $
b10000001010101111 &
b11001 '
b100110 (
b1010000110001111 *
b1010100111111000 +
b110001000 -
b101001010 .
b101001011 /
b1001011 0
b1010000110001111 1
b1010100111111000 2

#390000
b101011010011111 !
b1001010001011100 "
b1110101011111100 $
0%
b10100101110001000 &
b11010 '
b100111 (
b101011010011111 *
b1001010001011100 +
b11111100 -
b11101010 .
b11101011 /
b11101010 0
b101011010011111 1
b1001010001011100 2

#400000
b11011110001001 !
b11001001001001 "
0#
b110100111010010 $
b1110101011111100 &
b11011 '
b101000 (
b11011110001001 *
b11001001001001 +
0,
b11010010 -
b1101001 .
b1101010 /
b1101001 0
b11011110001001 1
b11001001001001 2
03

#410000
b1100000011010111 !
b1111110001010001 "
b1011110100101000 $
1%
b110100111010010 &
b11100 '
b101001 (
b1100000011010111 *
b1111110001010001 +
b100101000 -
b110111100 .
b110111101 /
b10111101 0
b1100000011010111 1
b1111110001010001 2

#420000
b111111100001100 !
b1100111011000010 "
b100110111001110 $
b11011110100101000 &
b11101 '
b101010 (
b111111100001100 *
b1100111011000010 +
b11001110 -
b101001101 .
b101001110 /
b1001101 0
b111111100001100 1
b1100111011000010 2

#430000
b101101001110111 !
b1110110100111101 "
b100011110110100 $
b10100110111001110 &
b11110 '
b101011 (
b101101001110111 *
b1110110100111101 +
b10110100 -
b101000111 .
b101001000 /
b1000111 0
b101101001110111 1
b1110110100111101 2

#440000
b1111110 !
b1000000101101101 "
1#
b1000000111101100 $
0%
b10100011110110100 &
b11111 '
b101100 (
b1111110 *
b1000000101101101 +
1,
b11101100 -
b10000001 .
b10000010 /
b10000001 0
b1111110 1
b1000000101101101 2
13

#450000
b1000111100011111 !
b1111011011010011 "
b1000010111110011 $
1%
b1000000111101100 &
b100000 '
b101101 (
b1000111100011111 *
b1111011011010011 +
b11110011 -
b110000101 .
b110000110 /
b10000101 0
b1000111100011111 1
b1111011011010011 2

#460000
b1000100001111000 !
b101100101011011 "
b1110000111010100 $
0%
b11000010111110011 &
b100001 '
b101110 (
b1000100001111000 *
b101100101011011 +
b11010100 -
b11100001 .
b11100010 /
b11100001 0
b1000100001111000 1
b101100101011011 2

#470000
b1010111000111111 !
b1010111100101010 "
0#
b101110101101001 $
1%
b1110000111010100 &
b100010 '
b101111 (
b1010111000111111 *
b1010111100101010 +
0,
b1101001 -
b101011101 .
b101011110 /
b1011101 0
b1010111000111111 1
b1010111100101010 2
03

#480000
b11100010000110 !
b110010001110 "
b100010100010100 $
0%
b10101110101101001 &
b100011 '
b110000 (
b11100010000110 *
b110010001110 +
b100010100 -
b1000100 .
b1000101 /
b1000101 0
b11100010000110 1
b110010001110 2

#490000
b1001100111111010 !
b1011110000100110 "
1#
b101011000100001 $
1%
b100010100010100 &
b100100 '
b110001 (
b1001100111111010 *
b1011110000100110 +
1,
b100100001 -
b101010101 .
b101010110 /
b1010110 0
b1001100111111010 1
b1011110000100110 2
13

#500000
b1011010010100011 !
b1010100000101111 "
b101110011010011 $
b10101011000100001 &
b100101 '
b110010 (
b1011010010100011 *
b1010100000101111 +
b11010011 -
b101011100 .
b101011101 /
b1011100 0
b1011010010100011 1
b1010100000101111 2

#510000
b101011001011111 !
b110101000100 "
b110001110100100 $
0%
b10101110011010011 &
b100110 '
b110011 (
b101011001011111 *
b110101000100 +
b10100100 -
b1100011 .
b1100100 /
b1100011 0
b101011001011111 1
b110101000100 2

#520000
b11011011001011 !
b1101011100110 "
0#
b101000110110001 $
b110001110100100 &
b100111 '
b110100 (
b11011011001011 *
b1101011100110 +
0,
b110110001 -
b1010000 .
b1010001 /
b1010001 0
b11011011001011 1
b1101011100110 2
03

#530000
b1100000100101001 !
b1110001011101101 "
b1010010000010110 $
1%
b101000110110001 &
b101000 '
b110101 (
b1100000100101001 *
b1110001011101101 +
b100010110 -
b110100011 .
b110100100 /
b10100100 0
b1100000100101001 1
b1110001011101101 2

#540000
b1011011001100101 !
b1110001010110101 "
1#
b1001100100011011 $
b11010010000010110 &
b101001 '
b110110 (
b1011011001100101 *
b1110001010110101 +
1,
b100011011 -
b110011000 .
b110011001 /
b10011001 0
b1011011001100101 1
b1110001010110101 2
13

#550000
b1100101111001 !
b1111111101000100 "
0#
b1100010111101 $
b11001100100011011 &
b101010 '
b110111 (
b1100101111001 *
b1111111101000100 +
0,
b10111101 -
b100011000 .
b100011001 /
b11000 0
b1100101111001 1
b1111111101000100 2
03

#560000
b101100101010 !
b1010110110101011 "
b1011100011010101 $
0%
b10001100010111101 &
b101011 '
b111000 (
b101100101010 *
b1010110110101011 +
b11010101 -
b10111000 .
b10111001 /
b10111000 0
b101100101010 1
b1010110110101011 2

#570000
b1010110111011100 !
b1011110010011010 "
1#
b110101001110111 $
1%
b1011100011010101 &
b101100 '
b111001 (
b1010110111011100 *
b1011110010011010 +
1,
b101110111 -
b101101001 .
b101101010 /
b1101010 0
b1010110111011100 1
b1011110010011010 2
13

#580000
b1011000011 !
b1110110101010110 "
0#
b1111000000011001 $
0%
b10110101001110111 &
b101101 '
b111010 (
b1011000011 *
b1110110101010110 +
0,
b100011001 -
b11101111 .
b11110000 /
b11110000 0
b1011000011 1
b1110110101010110 2
03

#590000
b111011001100111 !
b11010000001010 "
b1010101001110001 $
b1111000000011001 &
b101110 '
b111011 (
b111011001100111 *
b11010000001010 +
b1110001 -
b10101010 .
b10101011 /
b10101010 0
b111011001100111 1
b11010000001010 2

#600000
b1000101000111000 !
b1000011101111001 "
b1000110110001 $
1%
b1010101001110001 &
b101111 '
b111100 (
b1000101000111000 *
b1000011101111001 +
b10110001 -
b100010001 .
b100010010 /
b10001 0
b1000101000111000 1
b1000011101111001 2

#610000
b1011111110010100 !
b101110110010011 "
b1110100100111 $
b10001000110110001 &
b110000 '
b111101 (
b1011111110010100 *
b101110110010011 +
b100100111 -
b100011100 .
b100011101 /
b11101 0
b1011111110010100 1
b101110110010011 2

#620000
b1100101001011001 !
b110100111011011 "
1#
b11010000110101 $
b10001110100100111 &
b110001 '
b111110 (
b1100101001011001 *
b110100111011011 +
1,
b100110101 -
b100110011 .
b100110100 /
b110100 0
b1100101001011001 1
b110100111011011 2
13

#630000
b1011011111011001 !
b10011001101101 "
0#
b1101111001000110 $
0%
b10011010000110101 &
b110010 '
b111111 (
b1011011111011001 *
b10011001101101 +
0,
b101000110 -
b11011101 .
b11011110 /
b11011110 0
b1011011111011001 1
b10011001101101 2
03

#640000
b100100111001010 !
b10110110110110 "
1#
b111011110000001 $
b1101111001000110 &
b110011 '
b1000000 (
b100100111001010 *
b10110110110110 +
1,
b110000001 -
b1110110 .
b1110111 /
b1110111 0
b100100111001010 1
b10110110110110 2
13

#650000
b1101001000110 !
b1001101100000100 "
b1011010101001011 $
b111011110000001 &
b110100 '
b1000001 (
b1101001000110 *
b1001101100000100 +
b1001011 -
b10110101 .
b10110110 /
b10110101 0
b1101001000110 1
b1001101100000100 2

#660000
b11101101001 !
b1011101010110100 "
0#
b1100001000011101 $
b1011010101001011 &
b110101 '
b1000010 (
b11101101001 *
b1011101010110100 +
0,
b100011101 -
b11000001 .
b11000010 /
b11000010 0
b11101101001 1
b1011101010110100 2
03

#670000
b1101100100101000 !
b10000101101 "
1#
b1101110101010110 $
b1100001000011101 &
b110110 '
b1000011 (
b1101100100101000 *
b10000101101 +
1,
b1010110 -
b11011101 .
b11011110 /
b11011101 0
b1101100100101000 1
b10000101101 2
13

#680000
b1001110000101110 !
b1110010000001000 "
0#
b1000000000110110 $
1%
b1101110101010110 &
b110111 '
b1000100 (
b1001110000101110 *
b1110010000001000 +
0,
b110110 -
b110000000 .
b110000001 /
b10000000 0
b1001110000101110 1
b1110010000001000 2
03

#690000
b1010011011111101 !
b11100101001 "
b1010111000100110 $
0%
b11000000000110110 &
b111000 '
b1000101 (
b1010011011111101 *
b11100101001 +
b100100110 -
b10101101 .
b10101110 /
b10101110 0
b1010011011111101 1
b11100101001 2

#700000
b110011110000110 !
b100011011010 "
1#
b111000001100001 $
b1010111000100110 &
b111001 '
b1000110 (
b110011110000110 *
b100011011010 +
1,
b101100001 -
b1101111 .
b1110000 /
b1110000 0
b110011110000110 1
b100011011010 2
13

#710000
b1010011101100110 !
b1100010001110000 "
b110101111010111 $
1%
b111000001100001 &
b111010 '
b1000111 (
b1010011101100110 *
b1100010001110000 +
b11010111 -
b101101011 .
b101101100 /
b1101011 0
b1010011101100110 1
b1100010001110000 2

#720000
b1001100110111010 !
b1011001101011110 "
0#
b100110100011000 $
b10110101111010111 &
b111011 '
b1001000 (
b1001100110111010 *
b1011001101011110 +
0,
b100011000 -
b101001100 .
b101001101 /
b1001101 0
b1001100110111010 1
b1011001101011110 2
03

#730000
b10111010101 !
b1111011000011010 "
1#
b1111101111110000 $
0%
b10100110100011000 &
b111100 '
b1001001 (
b10111010101 *
b1111011000011010 +
1,
b11110000 -
b11111011 .
b11111100 /
b11111011 0
b10111010101 1
b1111011000011010 2
13

#740000
b110000100110111 !
b11011110010110 "
0#
b1001100011001101 $
b1111101111110000 &
b111101 '
b1001010 (
b110000100110111 *
b11011110010110 +
0,
b11001101 -
b10011000 .
b10011001 /
b10011000 0
b110000100110111 1
b11011110010110 2
03

#750000
b1001111100100110 !
b1101010110110 "
1#
b1011100111011101 $
b1001100011001101 &
b111110 '
b1001011 (
b1001111100100110 *
b1101010110110 +
1,
b11011101 -
b10111001 .
b10111010 /
b10111001 0
b1001111100100110 1
b1101010110110 2
13

#760000
b111111011100 !
b101011110000110 "
0#
b110011101100010 $
b1011100111011101 &
b111111 '
b1001100 (
b111111011100 *
b101011110000110 +
0,
b101100010 -
b1100110 .
b1100111 /
b1100111 0
b111111011100 1
b101011110000110 2
03

#770000
b1001101101111110 !
b1000000011011011 "
1#
b1110001011010 $
1%
b110011101100010 &
b1000000 '
b1001101 (
b1001101101111110 *
b1000000011011011 +
1,
b101011010 -
b100011011 .
b100011100 /
b11100 0
b1001101101111110 1
b1000000011011011 2
13

#780000
b10101101111001 !
b1110010011111010 "
b1000001110100 $
b10001110001011010 &
b1000001 '
b1001110 (
b10101101111001 *
b1110010011111010 +
b101110100 -
b100001111 .
b100010000 /
b10000 0
b10101101111001 1
b1110010011111010 2

#790000
b100100010111 !
b111100010100001 "
0#
b1000000110111000 $
0%
b10001000001110100 &
b1000010 '
b1001111 (
b100100010111 *
b111100010100001 +
0,
b10111000 -
b10000001 .
b10000010 /
b10000001 0
b100100010111 1
b111100010100001 2
03

#800000
b1001011001010000 !
b101100111110101 "
1#
b1111000001000110 $
b1000000110111000 &
b1000011 '
b1010000 (
b1001011001010000 *
b101100111110101 +
1,
b101000110 -
b11101111 .
b11110000 /
b11110000 0
b1001011001010000 1
b101100111110101 2
13

#810000
b1000101000101001 !
b111010111000001 "
b1111111111101011 $
b1111000001000110 &
b1000100 '
b1010001 (
b1000101000101001 *
b111010111000001 +
b11101011 -
b11111111 .
b100000000 /
b11111111 0
b1000101000101001 1
b111010111000001 2

#820000
b1011010010011000 !
b111101101001011 "
b10111111100100 $
1%
b1111111111101011 &
b1000101 '
b1010010 (
b1011010010011000 *
b111101101001011 +
b11100100 -
b100101111 .
b100110000 /
b101111 0
b1011010010011000 1
b111101101001011 2

#830000
b1110011011101100 !
b1011010001010 "
0#
b1111110101110110 $
0%
b10010111111100100 &
b1000110 '
b1010011 (
b1110011011101100 *
b1011010001010 +
0,
b101110110 -
b11111100 .
b11111101 /
b11111101 0
b1110011011101100 1
b1011010001010 2
03

#840000
b1000000010101000 !
b1111110110101001 "
1#
b111111001010010 $
1%
b1111110101110110 &
b1000111 '
b1010100 (
b1000000010101000 *
b1111110110101001 +
1,
b101010010 -
b101111101 .
b101111110 /
b1111110 0
b1000000010101000 1
b1111110110101001 2
13

#850000
b1011100100001110 !
b110011011100110 "
b1111111110101 $
b10111111001010010 &
b1001000 '
b1010101 (
b1011100100001110 *
b110011011100110 +
b11110101 -
b100011111 .
b100100000 /
b11111 0
b1011100100001110 1
b110011011100110 2

#860000
b1011010100101010 !
b1110100101010 "
b1101001001010101 $
0%
b10001111111110101 &
b1001001 '
b1010110 (
b1011010100101010 *
b1110100101010 +
b1010101 -
b11010010 .
b11010011 /
b11010010 0
b1011010100101010 1
b1110100101010 2

#870000
b1111111110011110 !
b1110011000111000 "
b1110010111010111 $
1%
b1101001001010101 &
b1001010 '
b1010111 (
b1111111110011110 *
b1110011000111000 +
b11010111 -
b111100101 .
b111100110 /
b11100101 0
b1111111110011110 1
b1110011000111000 2

#880000
b1110001111001000 !
b100010111001010 "
b10100110010011 $
b11110010111010111 &
b1001011 '
b1011000 (
b1110001111001000 *
b100010111001010 +
b110010011 -
b100101000 .
b100101001 /
b101001 0
b1110001111001000 1
b100010111001010 2

#890000
b1100100101101011 !
b1010111011000111 "
0#
b111100000110010 $
b10010100110010011 &
b1001100 '
b1011001 (
b1100100101101011 *
b1010111011000111 +
0,
b100110010 -
b101110111 .
b101111000 /
b1111000 0
b1100100101101011 1
b1010111011000111 2
03

#900000
b1001110110111010 !
b1010101111000100 "
1#
b100100101111111 $
b10111100000110010 &
b1001101 '
b1011010 (
b1001110110111010 *
b1010101111000100 +
1,
b101111111 -
b101001000 .
b101001001 /
b1001001 0
b1001110110111010 1
b1010101111000100 2
13

#910000
b1101001110010010 !
b1001101010110100 "
b110111001000111 $
b10100100101111111 &
b1001110 '
b1011011 (
b1101001110010010 *
b1001101010110100 +
b101000111 -
b101101101 .
b101101110 /
b1101110 0
b1101001110010010 1
b1001101010110100 2

#920000
b1001000010000110 !
b1111010111111010 "
0#
b1000011010000000 $
b10110111001000111 &
b1001111 '
b1011100 (
b1001000010000110 *
b1111010111111010 +
0,
b110000000 -
b110000101 .
b110000110 /
b10000110 0
b1001000010000110 1
b1111010111111010 2
03

#930000
b10000100110010 !
b101111010111101 "
b111111111101111 $
0%
b11000011010000000 &
b1010000 '
b1011101 (
b10000100110010 *
b101111010111101 +
b11101111 -
b1111111 .
b10000000 /
b1111111 0
b10000100110010 1
b101111010111101 2

#940000
b1010010011100100 !
b1100111111001010 "
1#
b111010010101111 $
1%
b111111111101111 &
b1010001 '
b1011110 (
b1010010011100100 *
b1100111111001010 +
1,
b110101111 -
b101110011 .
b101110100 /
b1110100 0
b1010010011100100 1
b1100111111001010 2
13

#950000
b1010100010100001 !
b1010100110001110 "
b101001000110000 $
b10111010010101111 &
b1010010 '
b1011111 (
b1010100010100001 *
b1010100110001110 +
b100110000 -
b101010001 .
b101010010 /
b1010010 0
b1010100010100001 1
b1010100110001110 2

#960000
b1111000001011 !
b1001000011101111 "
b1010111011111011 $
0%
b10101001000110000 &
b1010011 '
b1100000 (
b1111000001011 *
b1001000011101111 +
b11111011 -
b10101110 .
b10101111 /
b10101110 0
b1111000001011 1
b1001000011101111 2

#970000
b1110010100110110 !
b100100001110101 "
b10110110101100 $
1%
b1010111011111011 &
b1010100 '
b1100001 (
b1110010100110110 *
b100100001110101 +
b10101100 -
b100101101 .
b100101110 /
b101101 0
b1110010100110110 1
b100100001110101 2

#980000
b1011111101101011 !
b1110011110001000 "
0#
b1010011011110011 $
b10010110110101100 &
b1010101 '
b1100010 (
b1011111101101011 *
b1110011110001000 +
0,
b11110011 -
b110100110 .
b110100111 /
b10100110 0
b1011111101101011 1
b1110011110001000 2
03

#990000
b1000000110011011 !
b100010110010010 "
b1100011100101101 $
0%
b11010011011110011 &
b1010110 '
b1100011 (
b1000000110011011 *
b100010110010010 +
b100101101 -
b11000110 .
b11000111 /
b11000111 0
b1000000110011011 1
b100010110010010 2

#1000000
b1110000000101101 !
b101111101001011 "
b11111101111000 $
1%
b1100011100101101 &
b1010111 '
b1100100 (
b1110000000101101 *
b101111101001011 +
b1111000 -
b100111111 .
b101000000 /
b111111 0
b1110000000101101 1
b101111101001011 2
